Workbook

Sheet Start Here
A1: EXCEL LAB · 03 GST REGISTER — CONDITIONAL TOTALS
A2: A 120-invoice GST register: COUNTIF, SUMIFS with dates, a one-formula State × Rate matrix, MAXIFS, SUMPRODUCT array logic and an IGST/CGST boss round.
A4: HOW TO USE THIS WORKBOOK
A5: 1 | B5: Work through the lessons in order — each one is harder than the last (★ to ★★★★★).
A6: 2 | B6: Read the Concept box at the top of each lesson, then look at the data.
A7: 3 | B7: Type a FORMULA in each yellow cell. The Check column marks it ✓ or ✗ instantly.
A8: 4 | B8: Blue cells are inputs. Change them and watch every answer update — that is how you know your formula is really right.
A9: 5 | B9: Stuck? Read the Hint. Still stuck? The Solutions sheet shows the model answer and other ways to do it.
A11: COLOUR CODE
B12: Yellow — your answer goes here (always a formula)
B13: Blue — an input you can change
B14: ✓ Correct — marked automatically
B15: ✗ Check again — the result does not match
B16: ✎ You typed a value — replace it with a formula
A18: # | B18: Lesson | C18: Difficulty | D18: Tasks | E18: Solved | F18: Progress
A19: 1 | B19: L1 COUNTIF and SUMIF | C19: ★★☆☆☆ | D19: 5 | E19: =COUNTIF('L1 COUNTIF and SUMIF'!K9:K13,"✓*") -> 0 | F19: =IFERROR(E19/D19,0) -> 0
A20: 2 | B20: L2 SUMIFS with several conditio | C20: ★★★☆☆ | D20: 4 | E20: =COUNTIF('L2 SUMIFS with several conditio'!K9:K12,"✓*") -> 0 | F20: =IFERROR(E20/D20,0) -> 0
A21: 3 | B21: L3 The State × Rate matrix | C21: ★★★★☆ | D21: 3 | E21: =COUNTIF('L3 The State × Rate matrix'!K9:K11,"✓*") -> 0 | F21: =IFERROR(E21/D21,0) -> 0
A22: 4 | B22: L4 AVERAGEIFS, MAXIFS, MINIFS | C22: ★★★☆☆ | D22: 4 | E22: =COUNTIF('L4 AVERAGEIFS, MAXIFS, MINIFS'!K9:K12,"✓*") -> 0 | F22: =IFERROR(E22/D22,0) -> 0
A23: 5 | B23: L5 SUMPRODUCT conditions | C23: ★★★★☆ | D23: 4 | E23: =COUNTIF('L5 SUMPRODUCT conditions'!K9:K12,"✓*") -> 0 | F23: =IFERROR(E23/D23,0) -> 0
A24: 6 | B24: L6 Boss round — GST return summ | C24: ★★★★★ | D24: 5 | E24: =COUNTIF('L6 Boss round — GST return summ'!K9:K13,"✓*") -> 0 | F24: =IFERROR(E24/D24,0) -> 0
B25: OVERALL | D25: =SUM(D19:D24) -> 25 | E25: =SUM(E19:E24) -> 0 | F25: =IFERROR(E25/D25,0) -> 0
A27: Excel Lab — created by Pranay · excel-lab-by-pranay.vercel.app · free for every student

Sheet L1 COUNTIF and SUMIF
A1: LESSON 1 · COUNTIF AND SUMIF
A2: ★★☆☆☆ Count and total a 120-row GST register by one condition at a time.
A3: CONCEPT · COUNTIF(range, criteria) counts; SUMIF(range, criteria, sum_range) totals. Criteria are text in quotes: "Gujarat", ">=100000", "<>Delhi". Numbers can go bare: 5.
A8: Invoice | B8: Date | C8: Party | D8: State | E8: Taxable | F8: Rate | H8: # | I8: Task | J8: Your answer | K8: Check | L8: Hint
A9: INV-0001 | B9: 45870 | C9: Meera Pharma | D9: Maharashtra | E9: 102500 | F9: 5 | H9: 1 | I9: How many invoices were billed to Maharashtra? | K9: =IF(ISBLANK(J9),"◯ Not attempted",IF(NOT(_xlfn.ISFORMULA(J9)),"✎ Use a formula",IF(ISNUMBER(J9),IF(ABS(J9-$M$9)<0.005,"✓ Correct","✗ Check again"),"✗ Not a number"))) -> ◯ Not attempted | L9: COUNTIF(State column,"Maharashtra") | M9: =COUNTIF($D$9:$D$128,"Maharashtra") -> 29
A10: INV-0002 | B10: 46067 | C10: Kiran Agencies | D10: Delhi | E10: 293000 | F10: 28 | H10: 2 | I10: Total taxable value billed to Gujarat. | K10: =IF(ISBLANK(J10),"◯ Not attempted",IF(NOT(_xlfn.ISFORMULA(J10)),"✎ Use a formula",IF(ISNUMBER(J10),IF(ABS(J10-$M$10)<0.005,"✓ Correct","✗ Check again"),"✗ Not a number"))) -> ◯ Not attempted | L10: SUMIF: test range, criteria, sum range. | M10: =SUMIF($D$9:$D$128,"Gujarat",$E$9:$E$128) -> 5823000
A11: INV-0003 | B11: 45957 | C11: Orbit Systems | D11: Gujarat | E11: 407000 | F11: 5 | H11: 3 | I11: How many invoices are ₹1,00,000 or more? | K11: =IF(ISBLANK(J11),"◯ Not attempted",IF(NOT(_xlfn.ISFORMULA(J11)),"✎ Use a formula",IF(ISNUMBER(J11),IF(ABS(J11-$M$11)<0.005,"✓ Correct","✗ Check again"),"✗ Not a number"))) -> ◯ Not attempted | L11: ">=100000" in quotes. | M11: =COUNTIF($E$9:$E$128,">=100000") -> 104
A12: INV-0004 | B12: 46018 | C12: Sagar Metals | D12: Karnataka | E12: 398000 | F12: 5 | H12: 4 | I12: Total taxable value at the 5% rate. | K12: =IF(ISBLANK(J12),"◯ Not attempted",IF(NOT(_xlfn.ISFORMULA(J12)),"✎ Use a formula",IF(ISNUMBER(J12),IF(ABS(J12-$M$12)<0.005,"✓ Correct","✗ Check again"),"✗ Not a number"))) -> ◯ Not attempted | L12: The criteria can be a plain number. | M12: =SUMIF($F$9:$F$128,5,$E$9:$E$128) -> 8620000
A13: INV-0005 | B13: 45810 | C13: Meera Pharma | D13: Delhi | E13: 203000 | F13: 12 | H13: 5 | I13: How many invoices were NOT billed to Delhi? | K13: =IF(ISBLANK(J13),"◯ Not attempted",IF(NOT(_xlfn.ISFORMULA(J13)),"✎ Use a formula",IF(ISNUMBER(J13),IF(ABS(J13-$M$13)<0.005,"✓ Correct","✗ Check again"),"✗ Not a number"))) -> ◯ Not attempted | L13: "<>" means not equal. | M13: =COUNTIF($D$9:$D$128,"<>Delhi") -> 97
A14: INV-0006 | B14: 45896 | C14: ABC Traders | D14: Tamil Nadu | E14: 424000 | F14: 28
A15: INV-0007 | B15: 46109 | C15: ABC Traders | D15: Karnataka | E15: 120000 | F15: 12
A16: INV-0008 | B16: 45824 | C16: Nova Industries | D16: Karnataka | E16: 109000 | F16: 18
A17: INV-0009 | B17: 46107 | C17: Patel & Co | D17: Maharashtra | E17: 426500 | F17: 18
A18: INV-0010 | B18: 45875 | C18: Meera Pharma | D18: Delhi | E18: 451000 | F18: 5
A19: INV-0011 | B19: 45888 | C19: Meera Pharma | D19: Karnataka | E19: 327000 | F19: 12
A20: INV-0012 | B20: 45784 | C20: Bharat Electricals | D20: Karnataka | E20: 463000 | F20: 28
A21: INV-0013 | B21: 45886 | C21: Sagar Metals | D21: Gujarat | E21: 74500 | F21: 5
A22: INV-0014 | B22: 45996 | C22: Shree Enterprises | D22: Gujarat | E22: 96500 | F22: 28
A23: INV-0015 | B23: 45913 | C23: Nandini Foods | D23: Maharashtra | E23: 330000 | F23: 12
A24: INV-0016 | B24: 46068 | C24: Shree Enterprises | D24: Gujarat | E24: 364000 | F24: 28
A25: INV-0017 | B25: 45802 | C25: Deccan Supplies | D25: Maharashtra | E25: 72000 | F25: 12
... A128: INV-0120 | B128: 46058 | C128: Patel & Co | D128: Maharashtra | E128: 79000 | F128: 12

Sheet L2 SUMIFS with several conditio
A1: LESSON 2 · SUMIFS WITH SEVERAL CONDITIONS
A2: ★★★☆☆ Stack conditions — state, rate, amount band and date range.
A3: CONCEPT · SUMIFS(sum_range, range1, crit1, range2, crit2, …) — the sum range comes FIRST. All conditions must be true (AND). For a date range use two conditions on the same column: ">="&DATE(2026,1,1) and "<="&DATE(2026,3,31).
A8: Invoice | B8: Date | C8: Party | D8: State | E8: Taxable | F8: Rate | H8: # | I8: Task | J8: Your answer | K8: Check | L8: Hint
A9: INV-0001 | B9: 45870 | C9: Meera Pharma | D9: Maharashtra | E9: 102500 | F9: 5 | H9: 1 | I9: Taxable value in Maharashtra at 18%. | K9: =IF(ISBLANK(J9),"◯ Not attempted",IF(NOT(_xlfn.ISFORMULA(J9)),"✎ Use a formula",IF(ISNUMBER(J9),IF(ABS(J9-$M$9)<0.005,"✓ Correct","✗ Check again"),"✗ Not a number"))) -> ◯ Not attempted | L9: Two criteria pairs. | M9: =SUMIFS($E$9:$E$128,$D$9:$D$128,"Maharashtra",$F$9:$F$128,18) -> 1816500
A10: INV-0002 | B10: 46067 | C10: Kiran Agencies | D10: Delhi | E10: 293000 | F10: 28 | H10: 2 | I10: How many Karnataka invoices are between ₹50,000 and ₹2,00,000 (inclusive)? | K10: =IF(ISBLANK(J10),"◯ Not attempted",IF(NOT(_xlfn.ISFORMULA(J10)),"✎ Use a formula",IF(ISNUMBER(J10),IF(ABS(J10-$M$10)<0.005,"✓ Correct","✗ Check again"),"✗ Not a number"))) -> ◯ Not attempted | L10: The Taxable column appears twice — once for each end of the band. | M10: =COUNTIFS($D$9:$D$128,"Karnataka",$E$9:$E$128,">=50000",$E$9:$E$128,"<=200000") -> 6
A11: INV-0003 | B11: 45957 | C11: Orbit Systems | D11: Gujarat | E11: 407000 | F11: 5 | H11: 3 | I11: Taxable value billed to Delhi in the last quarter of the year (Jan–Mar 2026). | K11: =IF(ISBLANK(J11),"◯ Not attempted",IF(NOT(_xlfn.ISFORMULA(J11)),"✎ Use a formula",IF(ISNUMBER(J11),IF(ABS(J11-$M$11)<0.005,"✓ Correct","✗ Check again"),"✗ Not a number"))) -> ◯ Not attempted | L11: ">="&DATE(2026,1,1) joins the operator to a real date. | M11: =SUMIFS($E$9:$E$128,$D$9:$D$128,"Delhi",$B$9:$B$128,">="&DATE(2026,1,1),$B$9:$B$128,"<="&DATE(2026,3,31)) -> 1505000
A12: INV-0004 | B12: 46018 | C12: Sagar Metals | D12: Karnataka | E12: 398000 | F12: 5 | H12: 4 | I12: Taxable value billed to ABC Traders in Tamil Nadu. | K12: =IF(ISBLANK(J12),"◯ Not attempted",IF(NOT(_xlfn.ISFORMULA(J12)),"✎ Use a formula",IF(ISNUMBER(J12),IF(ABS(J12-$M$12)<0.005,"✓ Correct","✗ Check again"),"✗ Not a number"))) -> ◯ Not attempted | L12: Party and State criteria. | M12: =SUMIFS($E$9:$E$128,$C$9:$C$128,"ABC Traders",$D$9:$D$128,"Tamil Nadu") -> 697500
A13: INV-0005 | B13: 45810 | C13: Meera Pharma | D13: Delhi | E13: 203000 | F13: 12
A14: INV-0006 | B14: 45896 | C14: ABC Traders | D14: Tamil Nadu | E14: 424000 | F14: 28
A15: INV-0007 | B15: 46109 | C15: ABC Traders | D15: Karnataka | E15: 120000 | F15: 12
A16: INV-0008 | B16: 45824 | C16: Nova Industries | D16: Karnataka | E16: 109000 | F16: 18
A17: INV-0009 | B17: 46107 | C17: Patel & Co | D17: Maharashtra | E17: 426500 | F17: 18
A18: INV-0010 | B18: 45875 | C18: Meera Pharma | D18: Delhi | E18: 451000 | F18: 5
A19: INV-0011 | B19: 45888 | C19: Meera Pharma | D19: Karnataka | E19: 327000 | F19: 12
A20: INV-0012 | B20: 45784 | C20: Bharat Electricals | D20: Karnataka | E20: 463000 | F20: 28
A21: INV-0013 | B21: 45886 | C21: Sagar Metals | D21: Gujarat | E21: 74500 | F21: 5
A22: INV-0014 | B22: 45996 | C22: Shree Enterprises | D22: Gujarat | E22: 96500 | F22: 28
A23: INV-0015 | B23: 45913 | C23: Nandini Foods | D23: Maharashtra | E23: 330000 | F23: 12
A24: INV-0016 | B24: 46068 | C24: Shree Enterprises | D24: Gujarat | E24: 364000 | F24: 28
... A128: INV-0120 | B128: 46058 | C128: Patel & Co | D128: Maharashtra | E128: 79000 | F128: 12

Sheet L3 The State × Rate matrix
A1: LESSON 3 · THE STATE × RATE MATRIX
A2: ★★★★☆ Fill a 20-cell summary with ONE formula — the mixed-reference skill interviewers love.
A3: CONCEPT · In the grid, states run down the first column and rates across the top row. Lock the COLUMN of the state label and the ROW of the rate label. Write the formula once in the top-left cell, then fill right and down. If the $ signs are right, every cell is correct.
A8: Invoice | B8: Date | C8: Party | D8: State | E8: Taxable | F8: Rate | H8: # | I8: Task | J8: Your answer | K8: Check | L8: Hint
A9: INV-0001 | B9: 45870 | C9: Meera Pharma | D9: Maharashtra | E9: 102500 | F9: 5 | H9: 1 | I9: Fill the grid: taxable value for each state (rows) and rate (columns). | J9: → fill the grid below | K9: =IF(COUNT($J$15:$M$19)=0,"◯ Not attempted",IF(NOT(_xlfn.ISFORMULA(J15)),"✎ Use a formula",IFERROR(IF(SUMPRODUCT(--(ABS($J$15:$M$19-$O$15:$R$19)<0.01))=20,"✓ Correct","✗ "&(20-SUMPRODUCT(--(ABS($J$15:$M$19-$O$15:$R$19)<0.01)))&" cells differ"),"✗ Check the grid"))) -> ◯ Not attempted | L9: =SUMIFS($E$9:$E$128,$D$9:$D$128,$I15,$F$9:$F$128,J$14) in the top-left cell, then fill right and down.
A10: INV-0002 | B10: 46067 | C10: Kiran Agencies | D10: Delhi | E10: 293000 | F10: 28 | H10: 2 | I10: Grand total of the grid (it must equal the register total). | K10: =IF(ISBLANK(J10),"◯ Not attempted",IF(NOT(_xlfn.ISFORMULA(J10)),"✎ Use a formula",IF(ISNUMBER(J10),IF(ABS(J10-$N$10)<0.005,"✓ Correct","✗ Check again"),"✗ Not a number"))) -> ◯ Not attempted | L10: SUM the whole grid. | N10: =SUM($E$9:$E$128) -> 30844000
A11: INV-0003 | B11: 45957 | C11: Orbit Systems | D11: Gujarat | E11: 407000 | F11: 5 | H11: 3 | I11: Which state has the most business at 18%? | K11: =IF(ISBLANK(J11),"◯ Not attempted",IF(NOT(_xlfn.ISFORMULA(J11)),"✎ Use a formula",IF(UPPER(TRIM(J11&""))=UPPER(TRIM($N$11&"")),"✓ Correct","✗ Check again"))) -> ◯ Not attempted | L11: INDEX-MATCH on the 18% column of your grid. | N11: ="Karnataka" -> Karnataka
A12: INV-0004 | B12: 46018 | C12: Sagar Metals | D12: Karnataka | E12: 398000 | F12: 5
A13: INV-0005 | B13: 45810 | C13: Meera Pharma | D13: Delhi | E13: 203000 | F13: 12 | I13: State × Rate summary — one formula, filled right and down
A14: INV-0006 | B14: 45896 | C14: ABC Traders | D14: Tamil Nadu | E14: 424000 | F14: 28 | J14: 5 | K14: 12 | L14: 18 | M14: 28
A15: INV-0007 | B15: 46109 | C15: ABC Traders | D15: Karnataka | E15: 120000 | F15: 12 | I15: Maharashtra | O15: =SUMIFS($E$9:$E$128,$D$9:$D$128,$I15,$F$9:$F$128,J$14) -> 2446000 | P15: =SUMIFS($E$9:$E$128,$D$9:$D$128,$I15,$F$9:$F$128,K$14) -> 1659500 | Q15: =SUMIFS($E$9:$E$128,$D$9:$D$128,$I15,$F$9:$F$128,L$14) -> 1816500 | R15: =SUMIFS($E$9:$E$128,$D$9:$D$128,$I15,$F$9:$F$128,M$14) -> 404000
A16: INV-0008 | B16: 45824 | C16: Nova Industries | D16: Karnataka | E16: 109000 | F16: 18 | I16: Gujarat | O16: =SUMIFS($E$9:$E$128,$D$9:$D$128,$I16,$F$9:$F$128,J$14) -> 1032000 | P16: =SUMIFS($E$9:$E$128,$D$9:$D$128,$I16,$F$9:$F$128,K$14) -> 198500 | Q16: =SUMIFS($E$9:$E$128,$D$9:$D$128,$I16,$F$9:$F$128,L$14) -> 2266500 | R16: =SUMIFS($E$9:$E$128,$D$9:$D$128,$I16,$F$9:$F$128,M$14) -> 2326000
A17: INV-0009 | B17: 46107 | C17: Patel & Co | D17: Maharashtra | E17: 426500 | F17: 18 | I17: Karnataka | O17: =SUMIFS($E$9:$E$128,$D$9:$D$128,$I17,$F$9:$F$128,J$14) -> 2014000 | P17: =SUMIFS($E$9:$E$128,$D$9:$D$128,$I17,$F$9:$F$128,K$14) -> 2294000 | Q17: =SUMIFS($E$9:$E$128,$D$9:$D$128,$I17,$F$9:$F$128,L$14) -> 2280000 | R17: =SUMIFS($E$9:$E$128,$D$9:$D$128,$I17,$F$9:$F$128,M$14) -> 1371500
A18: INV-0010 | B18: 45875 | C18: Meera Pharma | D18: Delhi | E18: 451000 | F18: 5 | I18: Tamil Nadu | O18: =SUMIFS($E$9:$E$128,$D$9:$D$128,$I18,$F$9:$F$128,J$14) -> 1760000 | P18: =SUMIFS($E$9:$E$128,$D$9:$D$128,$I18,$F$9:$F$128,K$14) -> 1209500 | Q18: =SUMIFS($E$9:$E$128,$D$9:$D$128,$I18,$F$9:$F$128,L$14) -> 1018500 | R18: =SUMIFS($E$9:$E$128,$D$9:$D$128,$I18,$F$9:$F$128,M$14) -> 1508500
A19: INV-0011 | B19: 45888 | C19: Meera Pharma | D19: Karnataka | E19: 327000 | F19: 12 | I19: Delhi | O19: =SUMIFS($E$9:$E$128,$D$9:$D$128,$I19,$F$9:$F$128,J$14) -> 1368000 | P19: =SUMIFS($E$9:$E$128,$D$9:$D$128,$I19,$F$9:$F$128,K$14) -> 2377000 | Q19: =SUMIFS($E$9:$E$128,$D$9:$D$128,$I19,$F$9:$F$128,L$14) -> 5000 | R19: =SUMIFS($E$9:$E$128,$D$9:$D$128,$I19,$F$9:$F$128,M$14) -> 1489000
A20: INV-0012 | B20: 45784 | C20: Bharat Electricals | D20: Karnataka | E20: 463000 | F20: 28
A21: INV-0013 | B21: 45886 | C21: Sagar Metals | D21: Gujarat | E21: 74500 | F21: 5
A22: INV-0014 | B22: 45996 | C22: Shree Enterprises | D22: Gujarat | E22: 96500 | F22: 28
A23: INV-0015 | B23: 45913 | C23: Nandini Foods | D23: Maharashtra | E23: 330000 | F23: 12
A24: INV-0016 | B24: 46068 | C24: Shree Enterprises | D24: Gujarat | E24: 364000 | F24: 28
A25: INV-0017 | B25: 45802 | C25: Deccan Supplies | D25: Maharashtra | E25: 72000 | F25: 12
A26: INV-0018 | B26: 45846 | C26: Bharat Electricals | D26: Karnataka | E26: 352500 | F26: 5
A27: INV-0019 | B27: 46011 | C27: Bharat Electricals | D27: Delhi | E27: 5000 | F27: 18
A28: INV-0020 | B28: 45762 | C28: Shree Enterprises | D28: Delhi | E28: 132500 | F28: 12
A29: INV-0021 | B29: 46100 | C29: Nova Industries | D29: Delhi | E29: 348500 | F29: 28
A30: INV-0022 | B30: 46001 | C30: Sagar Metals | D30: Maharashtra | E30: 81500 | F30: 12
A31: INV-0023 | B31: 45780 | C31: Shree Enterprises | D31: Delhi | E31: 251500 | F31: 28
... A128: INV-0120 | B128: 46058 | C128: Patel & Co | D128: Maharashtra | E128: 79000 | F128: 12

Sheet L4 AVERAGEIFS, MAXIFS, MINIFS
A1: LESSON 4 · AVERAGEIFS, MAXIFS, MINIFS
A2: ★★★☆☆ Averages and extremes by segment.
A3: CONCEPT · AVERAGEIFS(avg_range, range1, crit1, …), MAXIFS(max_range, …), MINIFS(min_range, …) all follow the SUMIFS pattern: the result range comes first.
A8: Invoice | B8: Date | C8: Party | D8: State | E8: Taxable | F8: Rate | H8: # | I8: Task | J8: Your answer | K8: Check | L8: Hint
A9: INV-0001 | B9: 45870 | C9: Meera Pharma | D9: Maharashtra | E9: 102500 | F9: 5 | H9: 1 | I9: Average taxable value of Maharashtra invoices. | K9: =IF(ISBLANK(J9),"◯ Not attempted",IF(NOT(_xlfn.ISFORMULA(J9)),"✎ Use a formula",IF(ISNUMBER(J9),IF(ABS(J9-$M$9)<0.005,"✓ Correct","✗ Check again"),"✗ Not a number"))) -> ◯ Not attempted | L9: AVERAGEIFS, result range first. | M9: =AVERAGEIFS($E$9:$E$128,$D$9:$D$128,"Maharashtra") -> 218137.93
A10: INV-0002 | B10: 46067 | C10: Kiran Agencies | D10: Delhi | E10: 293000 | F10: 28 | H10: 2 | I10: Largest single invoice billed to Gujarat. | K10: =IF(ISBLANK(J10),"◯ Not attempted",IF(NOT(_xlfn.ISFORMULA(J10)),"✎ Use a formula",IF(ISNUMBER(J10),IF(ABS(J10-$M$10)<0.005,"✓ Correct","✗ Check again"),"✗ Not a number"))) -> ◯ Not attempted | L10: MAXIFS (Excel 2019+). | M10: =_xlfn.MAXIFS($E$9:$E$128,$D$9:$D$128,"Gujarat") -> 478500
A11: INV-0003 | B11: 45957 | C11: Orbit Systems | D11: Gujarat | E11: 407000 | F11: 5 | H11: 3 | I11: Smallest invoice at the 28% rate. | K11: =IF(ISBLANK(J11),"◯ Not attempted",IF(NOT(_xlfn.ISFORMULA(J11)),"✎ Use a formula",IF(ISNUMBER(J11),IF(ABS(J11-$M$11)<0.005,"✓ Correct","✗ Check again"),"✗ Not a number"))) -> ◯ Not attempted | L11: MINIFS with the rate as criteria. | M11: =_xlfn.MINIFS($E$9:$E$128,$F$9:$F$128,28) -> 3500
A12: INV-0004 | B12: 46018 | C12: Sagar Metals | D12: Karnataka | E12: 398000 | F12: 5 | H12: 4 | I12: Average taxable value of 18% invoices in Karnataka. | K12: =IF(ISBLANK(J12),"◯ Not attempted",IF(NOT(_xlfn.ISFORMULA(J12)),"✎ Use a formula",IF(ISNUMBER(J12),IF(ABS(J12-$M$12)<0.005,"✓ Correct","✗ Check again"),"✗ Not a number"))) -> ◯ Not attempted | L12: Two criteria. | M12: =AVERAGEIFS($E$9:$E$128,$D$9:$D$128,"Karnataka",$F$9:$F$128,18) -> 253333.33
A13: INV-0005 | B13: 45810 | C13: Meera Pharma | D13: Delhi | E13: 203000 | F13: 12
A14: INV-0006 | B14: 45896 | C14: ABC Traders | D14: Tamil Nadu | E14: 424000 | F14: 28
A15: INV-0007 | B15: 46109 | C15: ABC Traders | D15: Karnataka | E15: 120000 | F15: 12
A16: INV-0008 | B16: 45824 | C16: Nova Industries | D16: Karnataka | E16: 109000 | F16: 18
A17: INV-0009 | B17: 46107 | C17: Patel & Co | D17: Maharashtra | E17: 426500 | F17: 18
A18: INV-0010 | B18: 45875 | C18: Meera Pharma | D18: Delhi | E18: 451000 | F18: 5
A19: INV-0011 | B19: 45888 | C19: Meera Pharma | D19: Karnataka | E19: 327000 | F19: 12
A20: INV-0012 | B20: 45784 | C20: Bharat Electricals | D20: Karnataka | E20: 463000 | F20: 28
A21: INV-0013 | B21: 45886 | C21: Sagar Metals | D21: Gujarat | E21: 74500 | F21: 5
A22: INV-0014 | B22: 45996 | C22: Shree Enterprises | D22: Gujarat | E22: 96500 | F22: 28
A23: INV-0015 | B23: 45913 | C23: Nandini Foods | D23: Maharashtra | E23: 330000 | F23: 12
A24: INV-0016 | B24: 46068 | C24: Shree Enterprises | D24: Gujarat | E24: 364000 | F24: 28
... A128: INV-0120 | B128: 46058 | C128: Patel & Co | D128: Maharashtra | E128: 79000 | F128: 12

Sheet L5 SUMPRODUCT conditions
A1: LESSON 5 · SUMPRODUCT CONDITIONS
A2: ★★★★☆ Array logic: conditions SUMIFS can't express, like 'month = March'.
A3: CONCEPT · (D9:D128="Maharashtra") gives TRUE/FALSE per row; multiplying turns them into 1/0. SUMPRODUCT(test1*test2*amounts) sums only rows where every test is 1. + between tests means OR. MONTH(date range)=3 works inside SUMPRODUCT, which SUMIFS can't do.
A8: Invoice | B8: Date | C8: Party | D8: State | E8: Taxable | F8: Rate | H8: # | I8: Task | J8: Your answer | K8: Check | L8: Hint
A9: INV-0001 | B9: 45870 | C9: Meera Pharma | D9: Maharashtra | E9: 102500 | F9: 5 | H9: 1 | I9: Total GST payable on the register (Rate is a whole number). | K9: =IF(ISBLANK(J9),"◯ Not attempted",IF(NOT(_xlfn.ISFORMULA(J9)),"✎ Use a formula",IF(ISNUMBER(J9),IF(ABS(J9-$M$9)<0.005,"✓ Correct","✗ Check again"),"✗ Not a number"))) -> ◯ Not attempted | L9: SUMPRODUCT of two columns ÷ 100. | M9: =SUMPRODUCT($E$9:$E$128,$F$9:$F$128)/100 -> 4676910
A10: INV-0002 | B10: 46067 | C10: Kiran Agencies | D10: Delhi | E10: 293000 | F10: 28 | H10: 2 | I10: GST payable on Maharashtra invoices only. | K10: =IF(ISBLANK(J10),"◯ Not attempted",IF(NOT(_xlfn.ISFORMULA(J10)),"✎ Use a formula",IF(ISNUMBER(J10),IF(ABS(J10-$M$10)<0.005,"✓ Correct","✗ Check again"),"✗ Not a number"))) -> ◯ Not attempted | L10: Multiply the state test by taxable and rate. | M10: =SUMPRODUCT(($D$9:$D$128="Maharashtra")*$E$9:$E$128*$F$9:$F$128)/100 -> 761530
A11: INV-0003 | B11: 45957 | C11: Orbit Systems | D11: Gujarat | E11: 407000 | F11: 5 | H11: 3 | I11: Taxable value of invoices dated in March (any year). | K11: =IF(ISBLANK(J11),"◯ Not attempted",IF(NOT(_xlfn.ISFORMULA(J11)),"✎ Use a formula",IF(ISNUMBER(J11),IF(ABS(J11-$M$11)<0.005,"✓ Correct","✗ Check again"),"✗ Not a number"))) -> ◯ Not attempted | L11: MONTH(date range)=3 inside SUMPRODUCT. | M11: =SUMPRODUCT((MONTH($B$9:$B$128)=3)*$E$9:$E$128) -> 2124000
A12: INV-0004 | B12: 46018 | C12: Sagar Metals | D12: Karnataka | E12: 398000 | F12: 5 | H12: 4 | I12: How many invoices are from Gujarat OR Delhi? | K12: =IF(ISBLANK(J12),"◯ Not attempted",IF(NOT(_xlfn.ISFORMULA(J12)),"✎ Use a formula",IF(ISNUMBER(J12),IF(ABS(J12-$M$12)<0.005,"✓ Correct","✗ Check again"),"✗ Not a number"))) -> ◯ Not attempted | L12: + is OR. | M12: =SUMPRODUCT(($D$9:$D$128="Gujarat")+($D$9:$D$128="Delhi")) -> 45
A13: INV-0005 | B13: 45810 | C13: Meera Pharma | D13: Delhi | E13: 203000 | F13: 12
A14: INV-0006 | B14: 45896 | C14: ABC Traders | D14: Tamil Nadu | E14: 424000 | F14: 28
A15: INV-0007 | B15: 46109 | C15: ABC Traders | D15: Karnataka | E15: 120000 | F15: 12
A16: INV-0008 | B16: 45824 | C16: Nova Industries | D16: Karnataka | E16: 109000 | F16: 18
A17: INV-0009 | B17: 46107 | C17: Patel & Co | D17: Maharashtra | E17: 426500 | F17: 18
A18: INV-0010 | B18: 45875 | C18: Meera Pharma | D18: Delhi | E18: 451000 | F18: 5
A19: INV-0011 | B19: 45888 | C19: Meera Pharma | D19: Karnataka | E19: 327000 | F19: 12
A20: INV-0012 | B20: 45784 | C20: Bharat Electricals | D20: Karnataka | E20: 463000 | F20: 28
A21: INV-0013 | B21: 45886 | C21: Sagar Metals | D21: Gujarat | E21: 74500 | F21: 5
A22: INV-0014 | B22: 45996 | C22: Shree Enterprises | D22: Gujarat | E22: 96500 | F22: 28
A23: INV-0015 | B23: 45913 | C23: Nandini Foods | D23: Maharashtra | E23: 330000 | F23: 12
A24: INV-0016 | B24: 46068 | C24: Shree Enterprises | D24: Gujarat | E24: 364000 | F24: 28
... A128: INV-0120 | B128: 46058 | C128: Patel & Co | D128: Maharashtra | E128: 79000 | F128: 12

Sheet L6 Boss round — GST return summ
A1: LESSON 6 · BOSS ROUND — GST RETURN SUMMARY
A2: ★★★★★ Split output tax into IGST and CGST/SGST, then prove it ties.
A3: CONCEPT · Assume the seller is in Maharashtra. Sales to Maharashtra are intra-state: tax splits equally into CGST and SGST. Sales to any other state are inter-state: the whole tax is IGST. Answer cells can refer to other answer cells.
A8: Invoice | B8: Date | C8: Party | D8: State | E8: Taxable | F8: Rate | H8: # | I8: Task | J8: Your answer | K8: Check | L8: Hint
A9: INV-0001 | B9: 45870 | C9: Meera Pharma | D9: Maharashtra | E9: 102500 | F9: 5 | H9: 1 | I9: Total taxable value. | K9: =IF(ISBLANK(J9),"◯ Not attempted",IF(NOT(_xlfn.ISFORMULA(J9)),"✎ Use a formula",IF(ISNUMBER(J9),IF(ABS(J9-$M$9)<0.005,"✓ Correct","✗ Check again"),"✗ Not a number"))) -> ◯ Not attempted | L9: SUM. | M9: =SUM($E$9:$E$128) -> 30844000
A10: INV-0002 | B10: 46067 | C10: Kiran Agencies | D10: Delhi | E10: 293000 | F10: 28 | H10: 2 | I10: IGST — tax on sales outside Maharashtra. | K10: =IF(ISBLANK(J10),"◯ Not attempted",IF(NOT(_xlfn.ISFORMULA(J10)),"✎ Use a formula",IF(ISNUMBER(J10),IF(ABS(J10-$M$10)<0.005,"✓ Correct","✗ Check again"),"✗ Not a number"))) -> ◯ Not attempted | L10: <> "Maharashtra" inside SUMPRODUCT. | M10: =SUMPRODUCT(($D$9:$D$128<>"Maharashtra")*$E$9:$E$128*$F$9:$F$128)/100 -> 3915380
A11: INV-0003 | B11: 45957 | C11: Orbit Systems | D11: Gujarat | E11: 407000 | F11: 5 | H11: 3 | I11: CGST — half the tax on Maharashtra sales. | K11: =IF(ISBLANK(J11),"◯ Not attempted",IF(NOT(_xlfn.ISFORMULA(J11)),"✎ Use a formula",IF(ISNUMBER(J11),IF(ABS(J11-$M$11)<0.005,"✓ Correct","✗ Check again"),"✗ Not a number"))) -> ◯ Not attempted | L11: Divide by 200 = ÷100 then ÷2. | M11: =SUMPRODUCT(($D$9:$D$128="Maharashtra")*$E$9:$E$128*$F$9:$F$128)/200 -> 380765
A12: INV-0004 | B12: 46018 | C12: Sagar Metals | D12: Karnataka | E12: 398000 | F12: 5 | H12: 4 | I12: SGST — equal to CGST. | K12: =IF(ISBLANK(J12),"◯ Not attempted",IF(NOT(_xlfn.ISFORMULA(J12)),"✎ Use a formula",IF(ISNUMBER(J12),IF(ABS(J12-$M$12)<0.005,"✓ Correct","✗ Check again"),"✗ Not a number"))) -> ◯ Not attempted | L12: Refer to your CGST answer cell. | M12: =SUMPRODUCT(($D$9:$D$128="Maharashtra")*$E$9:$E$128*$F$9:$F$128)/200 -> 380765
A13: INV-0005 | B13: 45810 | C13: Meera Pharma | D13: Delhi | E13: 203000 | F13: 12 | H13: 5 | I13: Control check: total tax minus (IGST + CGST + SGST). Must be zero. | K13: =IF(ISBLANK(J13),"◯ Not attempted",IF(NOT(_xlfn.ISFORMULA(J13)),"✎ Use a formula",IF(ISNUMBER(J13),IF(ABS(J13-$M$13)<0.01,"✓ Correct","✗ Check again"),"✗ Not a number"))) -> ◯ Not attempted | L13: Total tax from SUMPRODUCT, minus your three answer cells. | M13: =0 -> 0
A14: INV-0006 | B14: 45896 | C14: ABC Traders | D14: Tamil Nadu | E14: 424000 | F14: 28
A15: INV-0007 | B15: 46109 | C15: ABC Traders | D15: Karnataka | E15: 120000 | F15: 12
A16: INV-0008 | B16: 45824 | C16: Nova Industries | D16: Karnataka | E16: 109000 | F16: 18
A17: INV-0009 | B17: 46107 | C17: Patel & Co | D17: Maharashtra | E17: 426500 | F17: 18
A18: INV-0010 | B18: 45875 | C18: Meera Pharma | D18: Delhi | E18: 451000 | F18: 5
A19: INV-0011 | B19: 45888 | C19: Meera Pharma | D19: Karnataka | E19: 327000 | F19: 12
A20: INV-0012 | B20: 45784 | C20: Bharat Electricals | D20: Karnataka | E20: 463000 | F20: 28
A21: INV-0013 | B21: 45886 | C21: Sagar Metals | D21: Gujarat | E21: 74500 | F21: 5
A22: INV-0014 | B22: 45996 | C22: Shree Enterprises | D22: Gujarat | E22: 96500 | F22: 28
A23: INV-0015 | B23: 45913 | C23: Nandini Foods | D23: Maharashtra | E23: 330000 | F23: 12
A24: INV-0016 | B24: 46068 | C24: Shree Enterprises | D24: Gujarat | E24: 364000 | F24: 28
A25: INV-0017 | B25: 45802 | C25: Deccan Supplies | D25: Maharashtra | E25: 72000 | F25: 12
... A128: INV-0120 | B128: 46058 | C128: Patel & Co | D128: Maharashtra | E128: 79000 | F128: 12

Sheet Solutions
A1: SOLUTIONS & OTHER WAYS — open only after you have tried
A2: Model answers are shapes, not the only answer. If your formula gives the same result, it is right — compare the logic.
A4: L1 COUNTIF and SUMIF ★★
A5: # | B5: Task | C5: Answer cell | D5: Model formula | E5: Other ways | F5: Why it works
A6: 1 | B6: How many invoices were billed to Maharashtra? | C6: J9 | D6: =COUNTIF($D$9:$D$128,"Maharashtra")
A7: 2 | B7: Total taxable value billed to Gujarat. | C7: J10 | D7: =SUMIF($D$9:$D$128,"Gujarat",$E$9:$E$128) | E7: =SUMIFS(E9:E128,D9:D128,"Gujarat")
A8: 3 | B8: How many invoices are ₹1,00,000 or more? | C8: J11 | D8: =COUNTIF($E$9:$E$128,">=100000")
A9: 4 | B9: Total taxable value at the 5% rate. | C9: J12 | D9: =SUMIF($F$9:$F$128,5,$E$9:$E$128)
A10: 5 | B10: How many invoices were NOT billed to Delhi? | C10: J13 | D10: =COUNTIF($D$9:$D$128,"<>Delhi") | E10: =COUNTA(A9:A128)-COUNTIF(D9:D128,"Delhi")
A12: L2 SUMIFS with several conditio ★★★
A13: # | B13: Task | C13: Answer cell | D13: Model formula | E13: Other ways | F13: Why it works
A14: 1 | B14: Taxable value in Maharashtra at 18%. | C14: J9 | D14: =SUMIFS($E$9:$E$128,$D$9:$D$128,"Maharashtra",$F$9:$F$128,18)
A15: 2 | B15: How many Karnataka invoices are between ₹50,000 and ₹2,00,000 (inclusive)? | C15: J10 | D15: =COUNTIFS($D$9:$D$128,"Karnataka",$E$9:$E$128,">=50000",$E$9:$E$128,"<=200000")
A16: 3 | B16: Taxable value billed to Delhi in the last quarter of the year (Jan–Mar 2026). | C16: J11 | D16: =SUMIFS($E$9:$E$128,$D$9:$D$128,"Delhi",$B$9:$B$128,">="&DATE(2026,1,1),$B$9:$B$128,"<="&DATE(2026,3,31)) | F16: Typing the date as text inside quotes breaks on computers with different date settings; DATE() never does.
A17: 4 | B17: Taxable value billed to ABC Traders in Tamil Nadu. | C17: J12 | D17: =SUMIFS($E$9:$E$128,$C$9:$C$128,"ABC Traders",$D$9:$D$128,"Tamil Nadu")
A19: L3 The State × Rate matrix ★★★★
A20: # | B20: Task | C20: Answer cell | D20: Model formula | E20: Other ways | F20: Why it works
A21: 1 | B21: Fill the grid: taxable value for each state (rows) and rate (columns). | C21: the grid | D21: =SUMIFS($E$9:$E$128,$D$9:$D$128,$I15,$F$9:$F$128,J$14) (first cell, then fill right and down) | E21: =SUMPRODUCT(($D$9:$D$128=$K12)*($F$9:$F$128=L$11)*$E$9:$E$128) A pivot table with State in Rows and Rate in Columns | F21: Mixed references move only in the direction you want.
A22: 2 | B22: Grand total of the grid (it must equal the register total). | C22: J10 | D22: =SUM($J$15:$M$19) | F22: A control total proves the summary is complete.
A23: 3 | B23: Which state has the most business at 18%? | C23: J11 | D23: =INDEX(I15:I19,MATCH(MAX(L15:L19),L15:L19,0))
A25: L4 AVERAGEIFS, MAXIFS, MINIFS ★★★
A26: # | B26: Task | C26: Answer cell | D26: Model formula | E26: Other ways | F26: Why it works
A27: 1 | B27: Average taxable value of Maharashtra invoices. | C27: J9 | D27: =AVERAGEIFS($E$9:$E$128,$D$9:$D$128,"Maharashtra")
A28: 2 | B28: Largest single invoice billed to Gujarat. | C28: J10 | D28: =MAXIFS($E$9:$E$128,$D$9:$D$128,"Gujarat") | E28: =MAX(IF(D9:D128="Gujarat",E9:E128)) — array formula for older Excel =AGGREGATE(14,6,E9:E128/(D9:D128="Gujarat"),1)
A29: 3 | B29: Smallest invoice at the 28% rate. | C29: J11 | D29: =MINIFS($E$9:$E$128,$F$9:$F$128,28)
A30: 4 | B30: Average taxable value of 18% invoices in Karnataka. | C30: J12 | D30: =AVERAGEIFS($E$9:$E$128,$D$9:$D$128,"Karnataka",$F$9:$F$128,18)
A32: L5 SUMPRODUCT conditions ★★★★
A33: # | B33: Task | C33: Answer cell | D33: Model formula | E33: Other ways | F33: Why it works
A34: 1 | B34: Total GST payable on the register (Rate is a whole number). | C34: J9 | D34: =SUMPRODUCT($E$9:$E$128,$F$9:$F$128)/100
A35: 2 | B35: GST payable on Maharashtra invoices only. | C35: J10 | D35: =SUMPRODUCT(($D$9:$D$128="Maharashtra")*$E$9:$E$128*$F$9:$F$128)/100
A36: 3 | B36: Taxable value of invoices dated in March (any year). | C36: J11 | D36: =SUMPRODUCT((MONTH($B$9:$B$128)=3)*$E$9:$E$128) | E36: =SUMIFS(E9:E128,B9:B128,">="&DATE(2026,3,1),B9:B128,"<="&DATE(2026,3,31)) — works here because the data covers one March
A37: 4 | B37: How many invoices are from Gujarat OR Delhi? | C37: J12 | D37: =SUMPRODUCT(($D$9:$D$128="Gujarat")+($D$9:$D$128="Delhi")) | E37: =COUNTIF(D9:D128,"Gujarat")+COUNTIF(D9:D128,"Delhi") =SUM(COUNTIF(D9:D128,{"Gujarat","Delhi"}))
A39: L6 Boss round — GST return summ ★★★★★
A40: # | B40: Task | C40: Answer cell | D40: Model formula | E40: Other ways | F40: Why it works
A41: 1 | B41: Total taxable value. | C41: J9 | D41: =SUM($E$9:$E$128)
A42: 2 | B42: IGST — tax on sales outside Maharashtra. | C42: J10 | D42: =SUMPRODUCT(($D$9:$D$128<>"Maharashtra")*$E$9:$E$128*$F$9:$F$128)/100
A43: 3 | B43: CGST — half the tax on Maharashtra sales. | C43: J11 | D43: =SUMPRODUCT(($D$9:$D$128="Maharashtra")*$E$9:$E$128*$F$9:$F$128)/200
A44: 4 | B44: SGST — equal to CGST. | C44: J12 | D44: =SUMPRODUCT(($D$9:$D$128="Maharashtra")*$E$9:$E$128*$F$9:$F$128)/200
A45: 5 | B45: Control check: total tax minus (IGST + CGST + SGST). Must be zero. | C45: J13 | D45: =SUMPRODUCT($E$9:$E$128,$F$9:$F$128)/100-(SUMPRODUCT(($D$9:$D$128<>"Maharashtra")*$E$9:$E$128*$F$9:$F$128)/100+2*SUMPRODUCT(($D$9:$D$128="Maharashtra")*$E$9:$E$128*$F$9:$F$128)/200) | F45: Every summary should prove itself against an independent total.
