Workbook

Sheet Start Here
A1: EXCEL LAB · 02 LOOKUP MASTERY
A2: VLOOKUP exact and approximate, INDEX-MATCH, two-way lookups, error-proofing and a two-condition boss round — against a real vendor master.
A4: HOW TO USE THIS WORKBOOK
A5: 1 | B5: Work through the lessons in order — each one is harder than the last (★ to ★★★★★).
A6: 2 | B6: Read the Concept box at the top of each lesson, then look at the data.
A7: 3 | B7: Type a FORMULA in each yellow cell. The Check column marks it ✓ or ✗ instantly.
A8: 4 | B8: Blue cells are inputs. Change them and watch every answer update — that is how you know your formula is really right.
A9: 5 | B9: Stuck? Read the Hint. Still stuck? The Solutions sheet shows the model answer and other ways to do it.
A11: COLOUR CODE
B12: Yellow — your answer goes here (always a formula)
B13: Blue — an input you can change
B14: ✓ Correct — marked automatically
B15: ✗ Check again — the result does not match
B16: ✎ You typed a value — replace it with a formula
A18: # | B18: Lesson | C18: Difficulty | D18: Tasks | E18: Solved | F18: Progress
A19: 1 | B19: L1 VLOOKUP exact match | C19: ★★☆☆☆ | D19: 4 | E19: =COUNTIF('L1 VLOOKUP exact match'!J9:J12,"✓*") -> 0 | F19: =IFERROR(E19/D19,0) -> 0
A20: 2 | B20: L2 Approximate match — slabs | C20: ★★★☆☆ | D20: 4 | E20: =COUNTIF('L2 Approximate match — slabs'!I9:I12,"✓*") -> 0 | F20: =IFERROR(E20/D20,0) -> 0
A21: 3 | B21: L3 INDEX-MATCH and left lookups | C21: ★★★☆☆ | D21: 4 | E21: =COUNTIF('L3 INDEX-MATCH and left lookups'!J9:J12,"✓*") -> 0 | F21: =IFERROR(E21/D21,0) -> 0
A22: 4 | B22: L4 Two-way lookup | C22: ★★★★☆ | D22: 4 | E22: =COUNTIF('L4 Two-way lookup'!K9:K12,"✓*") -> 0 | F22: =IFERROR(E22/D22,0) -> 0
A23: 5 | B23: L5 Error-proof lookups | C23: ★★★★☆ | D23: 4 | E23: =COUNTIF('L5 Error-proof lookups'!I9:I12,"✓*") -> 0 | F23: =IFERROR(E23/D23,0) -> 0
A24: 6 | B24: L6 Boss round — two-condition l | C24: ★★★★★ | D24: 4 | E24: =COUNTIF('L6 Boss round — two-condition l'!K9:K12,"✓*") -> 0 | F24: =IFERROR(E24/D24,0) -> 0
B25: OVERALL | D25: =SUM(D19:D24) -> 24 | E25: =SUM(E19:E24) -> 0 | F25: =IFERROR(E25/D25,0) -> 0
A27: Excel Lab — created by Pranay · excel-lab-by-pranay.vercel.app · free for every student

Sheet Vendor Master
A1: VENDOR MASTER
A2: Reference data used by the lessons. Don't edit it unless a lesson asks you to.
A8: Code | B8: Vendor | C8: City | D8: GSTIN | E8: Credit Days | F8: Category
A9: V001 | B9: Deccan Supplies | C9: Delhi | D9: 33AABCN4245G1ZV | E9: 60 | F9: Raw material
A10: V002 | B10: Orbit Systems | C10: Delhi | D10: 33AABCO1591Q1ZK | E10: 30 | F10: Packaging
A11: V003 | B11: Sagar Metals | C11: Surat | D11: 33AABCM6353P1ZE | E11: 60 | F11: Logistics
A12: V004 | B12: Nandini Foods | C12: Surat | D12: 27AABCY5167O1ZP | E12: 60 | F12: Services
A13: V005 | B13: Bharat Electricals | C13: Nagpur | D13: 27AABCU2636B1ZM | E13: 45 | F13: Raw material
A14: V006 | B14: Meera Pharma | C14: Surat | D14: 24AABCG3044L1ZE | E14: 30 | F14: Packaging
A15: V007 | B15: Kiran Agencies | C15: Surat | D15: 33AABCJ6745G1ZJ | E15: 45 | F15: Services
A16: V008 | B16: Vaibhav Textiles | C16: Surat | D16: 33AABCL1940T1ZG | E16: 60 | F16: Logistics
A17: V009 | B17: Patel & Co | C17: Bengaluru | D17: 07AABCL7707F1ZH | E17: 90 | F17: Services
A18: V010 | B18: Nova Industries | C18: Mumbai | D18: 29AABCG6314A1ZC | E18: 90 | F18: Logistics
A19: V011 | B19: Shree Enterprises | C19: Bengaluru | D19: 07AABCD5717X1ZF | E19: 45 | F19: IT
A20: V012 | B20: ABC Traders | C20: Ahmedabad | D20: 33AABCU3111R1ZF | E20: 90 | F20: Logistics
... A33: V025 | B33: Silverline Tools | C33: Bengaluru | D33: 33AABCK4894X1ZT | E33: 90 | F33: Packaging

Sheet L1 VLOOKUP exact match
A1: LESSON 1 · VLOOKUP EXACT MATCH
A2: ★★☆☆☆ Pull vendor details from the master into a purchase register.
A3: CONCEPT · VLOOKUP(what, table, column number, 0) searches the FIRST column of the table and returns a value from the column you name. The final 0 (or FALSE) forces an exact match — never leave it out. The master is on the 'Vendor Master' sheet; its data is A9:F33.
A8: Bill No | B8: Code | C8: Amount | D8: Vendor | E8: Credit Days | G8: # | H8: Task | I8: Your answer | J8: Check | K8: Hint
A9: B-1001 | B9: V008 | C9: 37800 | G9: 1 | H9: Fill Vendor: the vendor name for each bill's code. | I9: → fill column D | J9: =IF(COUNTA($D$9:$D$33)=0,"◯ Not attempted",IF(NOT(_xlfn.ISFORMULA(D9)),"✎ Use a formula",IFERROR(IF(SUMPRODUCT(--(UPPER(TRIM($D$9:$D$33&""))=UPPER(TRIM($M$9:$M$33&""))))=ROWS($D$9:$D$33),"✓ Correct","✗ "&(ROWS($D$9:$D$33)-SUMPRODUCT(--(UPPER(TRIM($D$9:$D$33&""))=UPPER(TRIM($M$9:$M$33&"")))))&" rows differ"),"✗ Check the column"))) -> ◯ Not attempted | K9: =VLOOKUP(B9,'Vendor Master'!$A$9:$F$33,2,0) — lock the table with $. | M9: =VLOOKUP(B9,'Vendor Master'!$A$9:$F$33,2,0) -> Vaibhav Textiles | N9: =VLOOKUP(B9,'Vendor Master'!$A$9:$F$33,5,0) -> 60
A10: B-1002 | B10: V012 | C10: 283900 | G10: 2 | H10: Fill Credit Days from the master. | I10: → fill column E | J10: =IF(COUNTA($E$9:$E$33)=0,"◯ Not attempted",IF(NOT(_xlfn.ISFORMULA(E9)),"✎ Use a formula",IFERROR(IF(SUMPRODUCT(--(ABS($E$9:$E$33-$N$9:$N$33)<0.01))=ROWS($E$9:$E$33),"✓ Correct","✗ "&(ROWS($E$9:$E$33)-SUMPRODUCT(--(ABS($E$9:$E$33-$N$9:$N$33)<0.01)))&" rows differ"),"✗ Check the column"))) -> ◯ Not attempted | K10: Same lookup, column 5. | M10: =VLOOKUP(B10,'Vendor Master'!$A$9:$F$33,2,0) -> ABC Traders | N10: =VLOOKUP(B10,'Vendor Master'!$A$9:$F$33,5,0) -> 90
A11: B-1003 | B11: V009 | C11: 263600 | G11: 3 | H11: Which city is vendor V017 in? | J11: =IF(ISBLANK(I11),"◯ Not attempted",IF(NOT(_xlfn.ISFORMULA(I11)),"✎ Use a formula",IF(UPPER(TRIM(I11&""))=UPPER(TRIM($L$11&"")),"✓ Correct","✗ Check again"))) -> ◯ Not attempted | K11: The lookup value can be typed in quotes. | L11: =VLOOKUP("V017",'Vendor Master'!$A$9:$F$33,3,0) -> Delhi | M11: =VLOOKUP(B11,'Vendor Master'!$A$9:$F$33,2,0) -> Patel & Co | N11: =VLOOKUP(B11,'Vendor Master'!$A$9:$F$33,5,0) -> 90
A12: B-1004 | B12: V007 | C12: 85100 | G12: 4 | H12: Total amount billed by vendors on 45-day credit. | J12: =IF(ISBLANK(I12),"◯ Not attempted",IF(NOT(_xlfn.ISFORMULA(I12)),"✎ Use a formula",IF(ISNUMBER(I12),IF(ABS(I12-$L$12)<0.005,"✓ Correct","✗ Check again"),"✗ Not a number"))) -> ◯ Not attempted | K12: SUMIF on your Credit Days column. | L12: =SUMPRODUCT((SUMIFS('Vendor Master'!$E$9:$E$33,'Vendor Master'!$A$9:$A$33,$B$9:$B$33)=45)*$C$9:$C$33) -> 907800 | M12: =VLOOKUP(B12,'Vendor Master'!$A$9:$F$33,2,0) -> Kiran Agencies | N12: =VLOOKUP(B12,'Vendor Master'!$A$9:$F$33,5,0) -> 45
A13: B-1005 | B13: V017 | C13: 84300 | M13: =VLOOKUP(B13,'Vendor Master'!$A$9:$F$33,2,0) -> Metro Freight | N13: =VLOOKUP(B13,'Vendor Master'!$A$9:$F$33,5,0) -> 90
A14: B-1006 | B14: V006 | C14: 185400 | M14: =VLOOKUP(B14,'Vendor Master'!$A$9:$F$33,2,0) -> Meera Pharma | N14: =VLOOKUP(B14,'Vendor Master'!$A$9:$F$33,5,0) -> 30
A15: B-1007 | B15: V001 | C15: 291200 | M15: =VLOOKUP(B15,'Vendor Master'!$A$9:$F$33,2,0) -> Deccan Supplies | N15: =VLOOKUP(B15,'Vendor Master'!$A$9:$F$33,5,0) -> 60
A16: B-1008 | B16: V002 | C16: 287300 | M16: =VLOOKUP(B16,'Vendor Master'!$A$9:$F$33,2,0) -> Orbit Systems | N16: =VLOOKUP(B16,'Vendor Master'!$A$9:$F$33,5,0) -> 30
A17: B-1009 | B17: V011 | C17: 122300 | M17: =VLOOKUP(B17,'Vendor Master'!$A$9:$F$33,2,0) -> Shree Enterprises | N17: =VLOOKUP(B17,'Vendor Master'!$A$9:$F$33,5,0) -> 45
A18: B-1010 | B18: V011 | C18: 86600 | M18: =VLOOKUP(B18,'Vendor Master'!$A$9:$F$33,2,0) -> Shree Enterprises | N18: =VLOOKUP(B18,'Vendor Master'!$A$9:$F$33,5,0) -> 45
A19: B-1011 | B19: V005 | C19: 61600 | M19: =VLOOKUP(B19,'Vendor Master'!$A$9:$F$33,2,0) -> Bharat Electricals | N19: =VLOOKUP(B19,'Vendor Master'!$A$9:$F$33,5,0) -> 45
A20: B-1012 | B20: V024 | C20: 166200 | M20: =VLOOKUP(B20,'Vendor Master'!$A$9:$F$33,2,0) -> Royal Castings | N20: =VLOOKUP(B20,'Vendor Master'!$A$9:$F$33,5,0) -> 90
A21: B-1013 | B21: V001 | C21: 12700 | M21: =VLOOKUP(B21,'Vendor Master'!$A$9:$F$33,2,0) -> Deccan Supplies | N21: =VLOOKUP(B21,'Vendor Master'!$A$9:$F$33,5,0) -> 60
A22: B-1014 | B22: V002 | C22: 127200 | M22: =VLOOKUP(B22,'Vendor Master'!$A$9:$F$33,2,0) -> Orbit Systems | N22: =VLOOKUP(B22,'Vendor Master'!$A$9:$F$33,5,0) -> 30
A23: B-1015 | B23: V025 | C23: 288600 | M23: =VLOOKUP(B23,'Vendor Master'!$A$9:$F$33,2,0) -> Silverline Tools | N23: =VLOOKUP(B23,'Vendor Master'!$A$9:$F$33,5,0) -> 90
A24: B-1016 | B24: V013 | C24: 135000 | M24: =VLOOKUP(B24,'Vendor Master'!$A$9:$F$33,2,0) -> Ganesh Logistics | N24: =VLOOKUP(B24,'Vendor Master'!$A$9:$F$33,5,0) -> 60
... A33: B-1025 | B33: V006 | C33: 288300 | M33: =VLOOKUP(B33,'Vendor Master'!$A$9:$F$33,2,0) -> Meera Pharma | N33: =VLOOKUP(B33,'Vendor Master'!$A$9:$F$33,5,0) -> 30

Sheet L2 Approximate match — slabs
A1: LESSON 2 · APPROXIMATE MATCH — SLABS
A2: ★★★☆☆ Use a sorted slab table to find commission rates — the same trick powers tax slabs.
A3: CONCEPT · VLOOKUP with TRUE (or no 4th argument) finds the LARGEST value that is not more than what you're looking for. The first column must be sorted ascending. The slab table is below the tasks, at the right.
A8: Salesperson | B8: Sales | C8: Rate | D8: Commission | F8: # | G8: Task | H8: Your answer | I8: Check | J8: Hint
A9: Aarav | B9: 404500 | F9: 1 | G9: Fill Rate: the commission rate for each salesperson's sales. | H9: → fill column C | I9: =IF(COUNTA($C$9:$C$28)=0,"◯ Not attempted",IF(NOT(_xlfn.ISFORMULA(C9)),"✎ Use a formula",IFERROR(IF(SUMPRODUCT(--(ABS($C$9:$C$28-$L$9:$L$28)<0.000001))=ROWS($C$9:$C$28),"✓ Correct","✗ "&(ROWS($C$9:$C$28)-SUMPRODUCT(--(ABS($C$9:$C$28-$L$9:$L$28)<0.000001)))&" rows differ"),"✗ Check the column"))) -> ◯ Not attempted | J9: =VLOOKUP(B9,slab table,2,TRUE) — lock the slab table with $. | L9: =VLOOKUP(B9,$G$16:$H$20,2,TRUE()) -> 0.035 | M9: =ROUND(B9*VLOOKUP(B9,$G$16:$H$20,2,TRUE()),0) -> 14158
A10: Diya | B10: 553500 | F10: 2 | G10: Fill Commission = Sales × Rate, rounded to whole rupees. | H10: → fill column D | I10: =IF(COUNTA($D$9:$D$28)=0,"◯ Not attempted",IF(NOT(_xlfn.ISFORMULA(D9)),"✎ Use a formula",IFERROR(IF(SUMPRODUCT(--(ABS($D$9:$D$28-$M$9:$M$28)<0.01))=ROWS($D$9:$D$28),"✓ Correct","✗ "&(ROWS($D$9:$D$28)-SUMPRODUCT(--(ABS($D$9:$D$28-$M$9:$M$28)<0.01)))&" rows differ"),"✗ Check the column"))) -> ◯ Not attempted | J10: =ROUND(B9*C9,0) | L10: =VLOOKUP(B10,$G$16:$H$20,2,TRUE()) -> 0.05 | M10: =ROUND(B10*VLOOKUP(B10,$G$16:$H$20,2,TRUE()),0) -> 27675
A11: Kabir | B11: 1557000 | F11: 3 | G11: Total commission payable. | I11: =IF(ISBLANK(H11),"◯ Not attempted",IF(NOT(_xlfn.ISFORMULA(H11)),"✎ Use a formula",IF(ISNUMBER(H11),IF(ABS(H11-$K$11)<0.005,"✓ Correct","✗ Check again"),"✗ Not a number"))) -> ◯ Not attempted | J11: SUM your Commission column. | K11: =SUMPRODUCT(ROUND($B$9:$B$28*LOOKUP($B$9:$B$28,$G$16:$G$20,$H$16:$H$20),0)) -> 1108875 | L11: =VLOOKUP(B11,$G$16:$H$20,2,TRUE()) -> 0.065 | M11: =ROUND(B11*VLOOKUP(B11,$G$16:$H$20,2,TRUE()),0) -> 101205
A12: Ishita | B12: 1394000 | F12: 4 | G12: Commission rate for a sale of exactly ₹2,50,000. | I12: =IF(ISBLANK(H12),"◯ Not attempted",IF(NOT(_xlfn.ISFORMULA(H12)),"✎ Use a formula",IF(ISNUMBER(H12),IF(ABS(H12-$K$12)<0.000001,"✓ Correct","✗ Check again"),"✗ Not a number"))) -> ◯ Not attempted | J12: An exact threshold lands on its own row. | K12: =VLOOKUP(250000,$G$16:$H$20,2,TRUE()) -> 0.035 | L12: =VLOOKUP(B12,$G$16:$H$20,2,TRUE()) -> 0.065 | M12: =ROUND(B12*VLOOKUP(B12,$G$16:$H$20,2,TRUE()),0) -> 90610
A13: Rohan | B13: 1379000 | L13: =VLOOKUP(B13,$G$16:$H$20,2,TRUE()) -> 0.065 | M13: =ROUND(B13*VLOOKUP(B13,$G$16:$H$20,2,TRUE()),0) -> 89635
A14: Meera | B14: 456500 | G14: Commission slabs (sorted ascending) | L14: =VLOOKUP(B14,$G$16:$H$20,2,TRUE()) -> 0.035 | M14: =ROUND(B14*VLOOKUP(B14,$G$16:$H$20,2,TRUE()),0) -> 15978
A15: Arjun | B15: 864500 | G15: From | H15: Rate | L15: =VLOOKUP(B15,$G$16:$H$20,2,TRUE()) -> 0.05 | M15: =ROUND(B15*VLOOKUP(B15,$G$16:$H$20,2,TRUE()),0) -> 43225
A16: Sana | B16: 1377000 | G16: 0 | H16: 0 | L16: =VLOOKUP(B16,$G$16:$H$20,2,TRUE()) -> 0.065 | M16: =ROUND(B16*VLOOKUP(B16,$G$16:$H$20,2,TRUE()),0) -> 89505
A17: Vikram | B17: 1462500 | G17: 100000 | H17: 0.02 | L17: =VLOOKUP(B17,$G$16:$H$20,2,TRUE()) -> 0.065 | M17: =ROUND(B17*VLOOKUP(B17,$G$16:$H$20,2,TRUE()),0) -> 95063
A18: Pooja | B18: 729500 | G18: 250000 | H18: 0.035 | L18: =VLOOKUP(B18,$G$16:$H$20,2,TRUE()) -> 0.05 | M18: =ROUND(B18*VLOOKUP(B18,$G$16:$H$20,2,TRUE()),0) -> 36475
A19: Neel | B19: 944500 | G19: 500000 | H19: 0.05 | L19: =VLOOKUP(B19,$G$16:$H$20,2,TRUE()) -> 0.05 | M19: =ROUND(B19*VLOOKUP(B19,$G$16:$H$20,2,TRUE()),0) -> 47225
A20: Riya | B20: 1311000 | G20: 1000000 | H20: 0.065 | L20: =VLOOKUP(B20,$G$16:$H$20,2,TRUE()) -> 0.065 | M20: =ROUND(B20*VLOOKUP(B20,$G$16:$H$20,2,TRUE()),0) -> 85215
A21: Kunal | B21: 1538000 | L21: =VLOOKUP(B21,$G$16:$H$20,2,TRUE()) -> 0.065 | M21: =ROUND(B21*VLOOKUP(B21,$G$16:$H$20,2,TRUE()),0) -> 99970
A22: Tara | B22: 505500 | L22: =VLOOKUP(B22,$G$16:$H$20,2,TRUE()) -> 0.05 | M22: =ROUND(B22*VLOOKUP(B22,$G$16:$H$20,2,TRUE()),0) -> 25275
A23: Omkar | B23: 604500 | L23: =VLOOKUP(B23,$G$16:$H$20,2,TRUE()) -> 0.05 | M23: =ROUND(B23*VLOOKUP(B23,$G$16:$H$20,2,TRUE()),0) -> 30225
A24: Zoya | B24: 432500 | L24: =VLOOKUP(B24,$G$16:$H$20,2,TRUE()) -> 0.035 | M24: =ROUND(B24*VLOOKUP(B24,$G$16:$H$20,2,TRUE()),0) -> 15138
A25: Aditya | B25: 64000 | L25: =VLOOKUP(B25,$G$16:$H$20,2,TRUE()) -> 0 | M25: =ROUND(B25*VLOOKUP(B25,$G$16:$H$20,2,TRUE()),0) -> 0
A26: Nisha | B26: 1305000 | L26: =VLOOKUP(B26,$G$16:$H$20,2,TRUE()) -> 0.065 | M26: =ROUND(B26*VLOOKUP(B26,$G$16:$H$20,2,TRUE()),0) -> 84825
A27: Farhan | B27: 1081500 | L27: =VLOOKUP(B27,$G$16:$H$20,2,TRUE()) -> 0.065 | M27: =ROUND(B27*VLOOKUP(B27,$G$16:$H$20,2,TRUE()),0) -> 70298
A28: Leela | B28: 943500 | L28: =VLOOKUP(B28,$G$16:$H$20,2,TRUE()) -> 0.05 | M28: =ROUND(B28*VLOOKUP(B28,$G$16:$H$20,2,TRUE()),0) -> 47175

Sheet L3 INDEX-MATCH and left lookups
A1: LESSON 3 · INDEX-MATCH AND LEFT LOOKUPS
A2: ★★★☆☆ Look up in any direction — including to the left, where VLOOKUP can't reach.
A3: CONCEPT · MATCH(what, list, 0) returns the position of a value. INDEX(list, position) returns the item at that position. Together: INDEX(return column, MATCH(value, search column, 0)). Here you know the vendor NAME and need its CODE, which sits to the left of the name in the master.
A8: PO No | B8: Vendor | C8: Amount | D8: Code | E8: GSTIN | G8: # | H8: Task | I8: Your answer | J8: Check | K8: Hint
A9: PO-501 | B9: Tulip Printers | C9: 184700 | G9: 1 | H9: Fill Code: the vendor code for each PO's vendor name. | I9: → fill column D | J9: =IF(COUNTA($D$9:$D$28)=0,"◯ Not attempted",IF(NOT(_xlfn.ISFORMULA(D9)),"✎ Use a formula",IFERROR(IF(SUMPRODUCT(--(UPPER(TRIM($D$9:$D$28&""))=UPPER(TRIM($M$9:$M$28&""))))=ROWS($D$9:$D$28),"✓ Correct","✗ "&(ROWS($D$9:$D$28)-SUMPRODUCT(--(UPPER(TRIM($D$9:$D$28&""))=UPPER(TRIM($M$9:$M$28&"")))))&" rows differ"),"✗ Check the column"))) -> ◯ Not attempted | K9: =INDEX(master Code column, MATCH(B9, master Vendor column, 0)) | M9: =INDEX('Vendor Master'!$A$9:$A$33,MATCH(B9,'Vendor Master'!$B$9:$B$33,0)) -> V023 | N9: =INDEX('Vendor Master'!$D$9:$D$33,MATCH(B9,'Vendor Master'!$B$9:$B$33,0)) -> 07AABCT5563Z1ZH
A10: PO-502 | B10: Kiran Agencies | C10: 23300 | G10: 2 | H10: Fill GSTIN for each PO's vendor. | I10: → fill column E | J10: =IF(COUNTA($E$9:$E$28)=0,"◯ Not attempted",IF(NOT(_xlfn.ISFORMULA(E9)),"✎ Use a formula",IFERROR(IF(SUMPRODUCT(--(UPPER(TRIM($E$9:$E$28&""))=UPPER(TRIM($N$9:$N$28&""))))=ROWS($E$9:$E$28),"✓ Correct","✗ "&(ROWS($E$9:$E$28)-SUMPRODUCT(--(UPPER(TRIM($E$9:$E$28&""))=UPPER(TRIM($N$9:$N$28&"")))))&" rows differ"),"✗ Check the column"))) -> ◯ Not attempted | K10: Same MATCH, different INDEX column. | M10: =INDEX('Vendor Master'!$A$9:$A$33,MATCH(B10,'Vendor Master'!$B$9:$B$33,0)) -> V007 | N10: =INDEX('Vendor Master'!$D$9:$D$33,MATCH(B10,'Vendor Master'!$B$9:$B$33,0)) -> 33AABCJ6745G1ZJ
A11: PO-503 | B11: ABC Traders | C11: 283800 | G11: 3 | H11: At what position in the master list does 'Metro Freight' appear? | J11: =IF(ISBLANK(I11),"◯ Not attempted",IF(NOT(_xlfn.ISFORMULA(I11)),"✎ Use a formula",IF(ISNUMBER(I11),IF(ABS(I11-$L$11)<0.005,"✓ Correct","✗ Check again"),"✗ Not a number"))) -> ◯ Not attempted | K11: MATCH on its own returns a position. | L11: =MATCH("Metro Freight",'Vendor Master'!$B$9:$B$33,0) -> 17 | M11: =INDEX('Vendor Master'!$A$9:$A$33,MATCH(B11,'Vendor Master'!$B$9:$B$33,0)) -> V012 | N11: =INDEX('Vendor Master'!$D$9:$D$33,MATCH(B11,'Vendor Master'!$B$9:$B$33,0)) -> 33AABCU3111R1ZF
A12: PO-504 | B12: Royal Castings | C12: 184500 | G12: 4 | H12: Category of the vendor on the largest PO. | J12: =IF(ISBLANK(I12),"◯ Not attempted",IF(NOT(_xlfn.ISFORMULA(I12)),"✎ Use a formula",IF(UPPER(TRIM(I12&""))=UPPER(TRIM($L$12&"")),"✓ Correct","✗ Check again"))) -> ◯ Not attempted | K12: First find the vendor with the MAX amount, then look up its category. | L12: =INDEX('Vendor Master'!$F$9:$F$33,MATCH(INDEX($B$9:$B$28,MATCH(MAX($C$9:$C$28),$C$9:$C$28,0)),'Vendor Master'!$B$9:$B$33,0)) -> Raw material | M12: =INDEX('Vendor Master'!$A$9:$A$33,MATCH(B12,'Vendor Master'!$B$9:$B$33,0)) -> V024 | N12: =INDEX('Vendor Master'!$D$9:$D$33,MATCH(B12,'Vendor Master'!$B$9:$B$33,0)) -> 33AABCE1853S1ZY
A13: PO-505 | B13: Sagar Metals | C13: 438000 | M13: =INDEX('Vendor Master'!$A$9:$A$33,MATCH(B13,'Vendor Master'!$B$9:$B$33,0)) -> V003 | N13: =INDEX('Vendor Master'!$D$9:$D$33,MATCH(B13,'Vendor Master'!$B$9:$B$33,0)) -> 33AABCM6353P1ZE
A14: PO-506 | B14: Zenith Software | C14: 200900 | M14: =INDEX('Vendor Master'!$A$9:$A$33,MATCH(B14,'Vendor Master'!$B$9:$B$33,0)) -> V022 | N14: =INDEX('Vendor Master'!$D$9:$D$33,MATCH(B14,'Vendor Master'!$B$9:$B$33,0)) -> 33AABCR2950I1ZH
A15: PO-507 | B15: Shree Enterprises | C15: 261800 | M15: =INDEX('Vendor Master'!$A$9:$A$33,MATCH(B15,'Vendor Master'!$B$9:$B$33,0)) -> V011 | N15: =INDEX('Vendor Master'!$D$9:$D$33,MATCH(B15,'Vendor Master'!$B$9:$B$33,0)) -> 07AABCD5717X1ZF
A16: PO-508 | B16: Kiran Agencies | C16: 307200 | M16: =INDEX('Vendor Master'!$A$9:$A$33,MATCH(B16,'Vendor Master'!$B$9:$B$33,0)) -> V007 | N16: =INDEX('Vendor Master'!$D$9:$D$33,MATCH(B16,'Vendor Master'!$B$9:$B$33,0)) -> 33AABCJ6745G1ZJ
A17: PO-509 | B17: Pioneer Plastics | C17: 244600 | M17: =INDEX('Vendor Master'!$A$9:$A$33,MATCH(B17,'Vendor Master'!$B$9:$B$33,0)) -> V020 | N17: =INDEX('Vendor Master'!$D$9:$D$33,MATCH(B17,'Vendor Master'!$B$9:$B$33,0)) -> 07AABCM8988L1ZJ
A18: PO-510 | B18: Meera Pharma | C18: 374300 | M18: =INDEX('Vendor Master'!$A$9:$A$33,MATCH(B18,'Vendor Master'!$B$9:$B$33,0)) -> V006 | N18: =INDEX('Vendor Master'!$D$9:$D$33,MATCH(B18,'Vendor Master'!$B$9:$B$33,0)) -> 24AABCG3044L1ZE
A19: PO-511 | B19: Everest Steel | C19: 320000 | M19: =INDEX('Vendor Master'!$A$9:$A$33,MATCH(B19,'Vendor Master'!$B$9:$B$33,0)) -> V019 | N19: =INDEX('Vendor Master'!$D$9:$D$33,MATCH(B19,'Vendor Master'!$B$9:$B$33,0)) -> 07AABCA1693N1ZB
A20: PO-512 | B20: ABC Traders | C20: 362600 | M20: =INDEX('Vendor Master'!$A$9:$A$33,MATCH(B20,'Vendor Master'!$B$9:$B$33,0)) -> V012 | N20: =INDEX('Vendor Master'!$D$9:$D$33,MATCH(B20,'Vendor Master'!$B$9:$B$33,0)) -> 33AABCU3111R1ZF
A21: PO-513 | B21: Ganesh Logistics | C21: 231000 | M21: =INDEX('Vendor Master'!$A$9:$A$33,MATCH(B21,'Vendor Master'!$B$9:$B$33,0)) -> V013 | N21: =INDEX('Vendor Master'!$D$9:$D$33,MATCH(B21,'Vendor Master'!$B$9:$B$33,0)) -> 24AABCB1254F1ZL
A22: PO-514 | B22: Crystal Glassworks | C22: 445700 | M22: =INDEX('Vendor Master'!$A$9:$A$33,MATCH(B22,'Vendor Master'!$B$9:$B$33,0)) -> V018 | N22: =INDEX('Vendor Master'!$D$9:$D$33,MATCH(B22,'Vendor Master'!$B$9:$B$33,0)) -> 27AABCO8696T1ZZ
A23: PO-515 | B23: Kiran Agencies | C23: 71900 | M23: =INDEX('Vendor Master'!$A$9:$A$33,MATCH(B23,'Vendor Master'!$B$9:$B$33,0)) -> V007 | N23: =INDEX('Vendor Master'!$D$9:$D$33,MATCH(B23,'Vendor Master'!$B$9:$B$33,0)) -> 33AABCJ6745G1ZJ
A24: PO-516 | B24: Royal Castings | C24: 79900 | M24: =INDEX('Vendor Master'!$A$9:$A$33,MATCH(B24,'Vendor Master'!$B$9:$B$33,0)) -> V024 | N24: =INDEX('Vendor Master'!$D$9:$D$33,MATCH(B24,'Vendor Master'!$B$9:$B$33,0)) -> 33AABCE1853S1ZY
... A28: PO-520 | B28: Tulip Printers | C28: 43700 | M28: =INDEX('Vendor Master'!$A$9:$A$33,MATCH(B28,'Vendor Master'!$B$9:$B$33,0)) -> V023 | N28: =INDEX('Vendor Master'!$D$9:$D$33,MATCH(B28,'Vendor Master'!$B$9:$B$33,0)) -> 07AABCT5563Z1ZH

Sheet L4 Two-way lookup
A1: LESSON 4 · TWO-WAY LOOKUP
A2: ★★★★☆ Find a value where a row and a column meet — the rate-card lookup.
A3: CONCEPT · INDEX(table, row number, column number) returns the cell where they cross. Use one MATCH for the row (product) and another for the column (region): INDEX(body, MATCH(product, products, 0), MATCH(region, regions, 0)).
A8: Order | B8: Product | C8: Region | D8: Qty | E8: Rate | F8: Value | H8: # | I8: Task | J8: Your answer | K8: Check | L8: Hint
A9: ORD-001 | B9: P3 | C9: South | D9: 20 | H9: 1 | I9: Fill Rate: the price for each order's product and region. | J9: → fill column E | K9: =IF(COUNTA($E$9:$E$33)=0,"◯ Not attempted",IF(NOT(_xlfn.ISFORMULA(E9)),"✎ Use a formula",IFERROR(IF(SUMPRODUCT(--(ABS($E$9:$E$33-$O$9:$O$33)<0.01))=ROWS($E$9:$E$33),"✓ Correct","✗ "&(ROWS($E$9:$E$33)-SUMPRODUCT(--(ABS($E$9:$E$33-$O$9:$O$33)<0.01)))&" rows differ"),"✗ Check the column"))) -> ◯ Not attempted | L9: INDEX(rate body, MATCH(B9,products,0), MATCH(C9,region headers,0)) | O9: =INDEX($J$16:$M$20,MATCH(B9,$I$16:$I$20,0),MATCH(C9,$J$15:$M$15,0)) -> 755 | P9: =D9*INDEX($J$16:$M$20,MATCH(B9,$I$16:$I$20,0),MATCH(C9,$J$15:$M$15,0)) -> 15100
A10: ORD-002 | B10: P2 | C10: East | D10: 144 | H10: 2 | I10: Fill Value = Qty × Rate. | J10: → fill column F | K10: =IF(COUNTA($F$9:$F$33)=0,"◯ Not attempted",IF(NOT(_xlfn.ISFORMULA(F9)),"✎ Use a formula",IFERROR(IF(SUMPRODUCT(--(ABS($F$9:$F$33-$P$9:$P$33)<0.01))=ROWS($F$9:$F$33),"✓ Correct","✗ "&(ROWS($F$9:$F$33)-SUMPRODUCT(--(ABS($F$9:$F$33-$P$9:$P$33)<0.01)))&" rows differ"),"✗ Check the column"))) -> ◯ Not attempted | L10: =D9*E9 | O10: =INDEX($J$16:$M$20,MATCH(B10,$I$16:$I$20,0),MATCH(C10,$J$15:$M$15,0)) -> 125 | P10: =D10*INDEX($J$16:$M$20,MATCH(B10,$I$16:$I$20,0),MATCH(C10,$J$15:$M$15,0)) -> 18000
A11: ORD-003 | B11: P4 | C11: South | D11: 135 | H11: 3 | I11: Total value of all orders. | K11: =IF(ISBLANK(J11),"◯ Not attempted",IF(NOT(_xlfn.ISFORMULA(J11)),"✎ Use a formula",IF(ISNUMBER(J11),IF(ABS(J11-$N$11)<0.005,"✓ Correct","✗ Check again"),"✗ Not a number"))) -> ◯ Not attempted | L11: SUM your Value column. | N11: =D9*INDEX($J$16:$M$20,MATCH(B9,$I$16:$I$20,0),MATCH(C9,$J$15:$M$15,0))+D10*INDEX($J$16:$M$20,MATCH(B10,$I$16:$I$20,0),MATCH(C10,$J$15:$M$15,0))+D11*INDEX($J$16:$M$20,MATCH(B11,$I$16:$I$20,0),MATCH(C11,$J$15:$M$15,0))+D12*INDEX($J$16:$M$20,MATCH(B12,$I$16:$I$20,0),MATCH(C12,$J$15:$M$15,0))+D13*INDEX($J$16:$M$20,MATCH(B13,$I$16:$I$20,0),MATCH(C13,$J$15:$M$15,0))+D14*INDEX($J$16:$M$20,MATCH(B14,$I$16:$I$20,0),MATCH(C14,$J$15:$M$15,0))+D15*INDEX($J$16:$M$20,MATCH(B15,$I$16:$I$20,0),MATCH(C15,$J$15:$M$15,0))+D16*INDEX($J$16:$M$20,MATCH(B16,$I$16:$I$20,0),MATCH(C16,$J$15:$M$15,0))+D17*INDEX($J$16:$M$20,MATCH(B17,$I$16:$I$20,0),MATCH(C17,$J$15:$M$15,0))+D18*INDEX($J$16:$M$20,MATCH(B18,$I$16:$I$20,0),MATCH(C18,$J$15:$M$15,0))+D19*INDEX($J$16:$M$20,MATCH(B19,$I$16:$I$20,0),MATCH(C19,$J$15:$M$15,0))+D20*INDEX($J$16:$M$20,MATCH(B20,$I$16:$I$20,0),MATCH(C20,$J$15:$M$15,0))+D21*INDEX($J$16:$M$20,MATCH(B21,$I$16:$I$20,0),MATCH(C21,$J$15:$M$15,0))+D22*INDEX($J$16:$M$20,MATCH(B22,$I$16:$I$20,0),MATCH(C22,$J$15:$M$15,0))+D23*INDEX($J$16:$M$20,MATCH(B23,$I$16:$I$20,0),MATCH(C23,$J$15:$M$15,0))+D24*INDEX($J$16:$M$20,MATCH(B24,$I$16:$I$20,0),MATCH(C24,$J$15:$M$15,0))+D25*INDEX($J$16:$M$20,MATCH(B25,$I$16:$I$20,0),MATCH(C25,$J$15:$M$15,0))+D26*INDEX($J$16:$M$20,MATCH(B26,$I$16:$I$20,0),MATCH(C26,$J$15:$M$15,0))+D27*INDEX($J$16:$M$20,MATCH(B27,$I$16:$I$20,0),MATCH(C27,$J$15:$M$15,0))+D28*INDEX($J$16:$M$20,MATCH(B28,$I$16:$I$20,0),MATCH(C28,$J$15:$M$15,0))+D29*INDEX($J$16:$M$20,MATCH(B29,$I$16:$I$20,0),MATCH(C29,$J$15:$M$15,0))+D30*INDEX($J$16:$M$20,MATCH(B30,$I$16:$I$20,0),MATCH(C30,$J$15:$M$15,0))+D31*INDEX($J$16:$M$20,MATCH(B31,$I$16:$I$20,0),MATCH(C31,$J$15:$M$15,0))+D32*INDEX($J$16:$M$20,MATCH(B32,$I$16:$I$20,0),MATCH(C32,$J$15:$M$15,0))+D33*INDEX($J$16:$M$20,MATCH(B33,$I$16:$I$20,0),MATCH(C33,$J$15:$M$15,0)) -> 1567530 | O11: =INDEX($J$16:$M$20,MATCH(B11,$I$16:$I$20,0),MATCH(C11,$J$15:$M$15,0)) -> 600 | P11: =D11*INDEX($J$16:$M$20,MATCH(B11,$I$16:$I$20,0),MATCH(C11,$J$15:$M$15,0)) -> 81000
A12: ORD-004 | B12: P3 | C12: South | D12: 55 | H12: 4 | I12: Rate for product P3 in the East region. | K12: =IF(ISBLANK(J12),"◯ Not attempted",IF(NOT(_xlfn.ISFORMULA(J12)),"✎ Use a formula",IF(ISNUMBER(J12),IF(ABS(J12-$N$12)<0.005,"✓ Correct","✗ Check again"),"✗ Not a number"))) -> ◯ Not attempted | L12: Type the product and region in quotes. | N12: =INDEX($J$16:$M$20,MATCH("P3",$I$16:$I$20,0),MATCH("East",$J$15:$M$15,0)) -> 215 | O12: =INDEX($J$16:$M$20,MATCH(B12,$I$16:$I$20,0),MATCH(C12,$J$15:$M$15,0)) -> 755 | P12: =D12*INDEX($J$16:$M$20,MATCH(B12,$I$16:$I$20,0),MATCH(C12,$J$15:$M$15,0)) -> 41525
A13: ORD-005 | B13: P3 | C13: West | D13: 9 | O13: =INDEX($J$16:$M$20,MATCH(B13,$I$16:$I$20,0),MATCH(C13,$J$15:$M$15,0)) -> 185 | P13: =D13*INDEX($J$16:$M$20,MATCH(B13,$I$16:$I$20,0),MATCH(C13,$J$15:$M$15,0)) -> 1665
A14: ORD-006 | B14: P5 | C14: South | D14: 8 | I14: Rate card (₹ per unit) | O14: =INDEX($J$16:$M$20,MATCH(B14,$I$16:$I$20,0),MATCH(C14,$J$15:$M$15,0)) -> 380 | P14: =D14*INDEX($J$16:$M$20,MATCH(B14,$I$16:$I$20,0),MATCH(C14,$J$15:$M$15,0)) -> 3040
A15: ORD-007 | B15: P1 | C15: South | D15: 162 | I15: Product | J15: North | K15: South | L15: East | M15: West | O15: =INDEX($J$16:$M$20,MATCH(B15,$I$16:$I$20,0),MATCH(C15,$J$15:$M$15,0)) -> 655 | P15: =D15*INDEX($J$16:$M$20,MATCH(B15,$I$16:$I$20,0),MATCH(C15,$J$15:$M$15,0)) -> 106110
A16: ORD-008 | B16: P2 | C16: West | D16: 219 | I16: P1 | J16: 435 | K16: 655 | L16: 865 | M16: 450 | O16: =INDEX($J$16:$M$20,MATCH(B16,$I$16:$I$20,0),MATCH(C16,$J$15:$M$15,0)) -> 205 | P16: =D16*INDEX($J$16:$M$20,MATCH(B16,$I$16:$I$20,0),MATCH(C16,$J$15:$M$15,0)) -> 44895
A17: ORD-009 | B17: P4 | C17: East | D17: 174 | I17: P2 | J17: 740 | K17: 425 | L17: 125 | M17: 205 | O17: =INDEX($J$16:$M$20,MATCH(B17,$I$16:$I$20,0),MATCH(C17,$J$15:$M$15,0)) -> 555 | P17: =D17*INDEX($J$16:$M$20,MATCH(B17,$I$16:$I$20,0),MATCH(C17,$J$15:$M$15,0)) -> 96570
A18: ORD-010 | B18: P3 | C18: East | D18: 177 | I18: P3 | J18: 235 | K18: 755 | L18: 215 | M18: 185 | O18: =INDEX($J$16:$M$20,MATCH(B18,$I$16:$I$20,0),MATCH(C18,$J$15:$M$15,0)) -> 215 | P18: =D18*INDEX($J$16:$M$20,MATCH(B18,$I$16:$I$20,0),MATCH(C18,$J$15:$M$15,0)) -> 38055
A19: ORD-011 | B19: P4 | C19: East | D19: 39 | I19: P4 | J19: 520 | K19: 600 | L19: 555 | M19: 780 | O19: =INDEX($J$16:$M$20,MATCH(B19,$I$16:$I$20,0),MATCH(C19,$J$15:$M$15,0)) -> 555 | P19: =D19*INDEX($J$16:$M$20,MATCH(B19,$I$16:$I$20,0),MATCH(C19,$J$15:$M$15,0)) -> 21645
A20: ORD-012 | B20: P1 | C20: East | D20: 247 | I20: P5 | J20: 485 | K20: 380 | L20: 455 | M20: 145 | O20: =INDEX($J$16:$M$20,MATCH(B20,$I$16:$I$20,0),MATCH(C20,$J$15:$M$15,0)) -> 865 | P20: =D20*INDEX($J$16:$M$20,MATCH(B20,$I$16:$I$20,0),MATCH(C20,$J$15:$M$15,0)) -> 213655
A21: ORD-013 | B21: P3 | C21: South | D21: 95 | O21: =INDEX($J$16:$M$20,MATCH(B21,$I$16:$I$20,0),MATCH(C21,$J$15:$M$15,0)) -> 755 | P21: =D21*INDEX($J$16:$M$20,MATCH(B21,$I$16:$I$20,0),MATCH(C21,$J$15:$M$15,0)) -> 71725
A22: ORD-014 | B22: P4 | C22: North | D22: 118 | O22: =INDEX($J$16:$M$20,MATCH(B22,$I$16:$I$20,0),MATCH(C22,$J$15:$M$15,0)) -> 520 | P22: =D22*INDEX($J$16:$M$20,MATCH(B22,$I$16:$I$20,0),MATCH(C22,$J$15:$M$15,0)) -> 61360
A23: ORD-015 | B23: P1 | C23: West | D23: 127 | O23: =INDEX($J$16:$M$20,MATCH(B23,$I$16:$I$20,0),MATCH(C23,$J$15:$M$15,0)) -> 450 | P23: =D23*INDEX($J$16:$M$20,MATCH(B23,$I$16:$I$20,0),MATCH(C23,$J$15:$M$15,0)) -> 57150
A24: ORD-016 | B24: P4 | C24: South | D24: 165 | O24: =INDEX($J$16:$M$20,MATCH(B24,$I$16:$I$20,0),MATCH(C24,$J$15:$M$15,0)) -> 600 | P24: =D24*INDEX($J$16:$M$20,MATCH(B24,$I$16:$I$20,0),MATCH(C24,$J$15:$M$15,0)) -> 99000
A25: ORD-017 | B25: P2 | C25: South | D25: 104 | O25: =INDEX($J$16:$M$20,MATCH(B25,$I$16:$I$20,0),MATCH(C25,$J$15:$M$15,0)) -> 425 | P25: =D25*INDEX($J$16:$M$20,MATCH(B25,$I$16:$I$20,0),MATCH(C25,$J$15:$M$15,0)) -> 44200
A26: ORD-018 | B26: P3 | C26: South | D26: 139 | O26: =INDEX($J$16:$M$20,MATCH(B26,$I$16:$I$20,0),MATCH(C26,$J$15:$M$15,0)) -> 755 | P26: =D26*INDEX($J$16:$M$20,MATCH(B26,$I$16:$I$20,0),MATCH(C26,$J$15:$M$15,0)) -> 104945
A27: ORD-019 | B27: P3 | C27: North | D27: 158 | O27: =INDEX($J$16:$M$20,MATCH(B27,$I$16:$I$20,0),MATCH(C27,$J$15:$M$15,0)) -> 235 | P27: =D27*INDEX($J$16:$M$20,MATCH(B27,$I$16:$I$20,0),MATCH(C27,$J$15:$M$15,0)) -> 37130
A28: ORD-020 | B28: P1 | C28: East | D28: 112 | O28: =INDEX($J$16:$M$20,MATCH(B28,$I$16:$I$20,0),MATCH(C28,$J$15:$M$15,0)) -> 865 | P28: =D28*INDEX($J$16:$M$20,MATCH(B28,$I$16:$I$20,0),MATCH(C28,$J$15:$M$15,0)) -> 96880
A29: ORD-021 | B29: P1 | C29: East | D29: 50 | O29: =INDEX($J$16:$M$20,MATCH(B29,$I$16:$I$20,0),MATCH(C29,$J$15:$M$15,0)) -> 865 | P29: =D29*INDEX($J$16:$M$20,MATCH(B29,$I$16:$I$20,0),MATCH(C29,$J$15:$M$15,0)) -> 43250
A30: ORD-022 | B30: P2 | C30: South | D30: 138 | O30: =INDEX($J$16:$M$20,MATCH(B30,$I$16:$I$20,0),MATCH(C30,$J$15:$M$15,0)) -> 425 | P30: =D30*INDEX($J$16:$M$20,MATCH(B30,$I$16:$I$20,0),MATCH(C30,$J$15:$M$15,0)) -> 58650
A31: ORD-023 | B31: P1 | C31: North | D31: 225 | O31: =INDEX($J$16:$M$20,MATCH(B31,$I$16:$I$20,0),MATCH(C31,$J$15:$M$15,0)) -> 435 | P31: =D31*INDEX($J$16:$M$20,MATCH(B31,$I$16:$I$20,0),MATCH(C31,$J$15:$M$15,0)) -> 97875
A32: ORD-024 | B32: P3 | C32: North | D32: 219 | O32: =INDEX($J$16:$M$20,MATCH(B32,$I$16:$I$20,0),MATCH(C32,$J$15:$M$15,0)) -> 235 | P32: =D32*INDEX($J$16:$M$20,MATCH(B32,$I$16:$I$20,0),MATCH(C32,$J$15:$M$15,0)) -> 51465
A33: ORD-025 | B33: P1 | C33: North | D33: 144 | O33: =INDEX($J$16:$M$20,MATCH(B33,$I$16:$I$20,0),MATCH(C33,$J$15:$M$15,0)) -> 435 | P33: =D33*INDEX($J$16:$M$20,MATCH(B33,$I$16:$I$20,0),MATCH(C33,$J$15:$M$15,0)) -> 62640

Sheet L5 Error-proof lookups
A1: LESSON 5 · ERROR-PROOF LOOKUPS
A2: ★★★★☆ Handle codes that aren't in the master — and count them, because that's the finding.
A3: CONCEPT · A lookup that finds nothing returns #N/A. IFERROR(formula, "Not in master") swaps any error for your text; IFNA does the same only for #N/A, so real mistakes stay visible. ISNA(MATCH(…)) is TRUE when a value is missing — perfect for counting exceptions.
A8: Bill No | B8: Code | C8: Amount | D8: Vendor | F8: # | G8: Task | H8: Your answer | I8: Check | J8: Hint
A9: B-2001 | B9: V009 | C9: 159000 | F9: 1 | G9: Fill Vendor, showing "Not in master" when the code is missing. | H9: → fill column D | I9: =IF(COUNTA($D$9:$D$33)=0,"◯ Not attempted",IF(NOT(_xlfn.ISFORMULA(D9)),"✎ Use a formula",IFERROR(IF(SUMPRODUCT(--(UPPER(TRIM($D$9:$D$33&""))=UPPER(TRIM($L$9:$L$33&""))))=ROWS($D$9:$D$33),"✓ Correct","✗ "&(ROWS($D$9:$D$33)-SUMPRODUCT(--(UPPER(TRIM($D$9:$D$33&""))=UPPER(TRIM($L$9:$L$33&"")))))&" rows differ"),"✗ Check the column"))) -> ◯ Not attempted | J9: Wrap the VLOOKUP in IFERROR(…,"Not in master"). | L9: =IFERROR(VLOOKUP(B9,'Vendor Master'!$A$9:$F$33,2,0),"Not in master") -> Patel & Co
A10: B-2002 | B10: V023 | C10: 122600 | F10: 2 | G10: How many bills have a code that isn't in the master? | I10: =IF(ISBLANK(H10),"◯ Not attempted",IF(NOT(_xlfn.ISFORMULA(H10)),"✎ Use a formula",IF(ISNUMBER(H10),IF(ABS(H10-$K$10)<0.005,"✓ Correct","✗ Check again"),"✗ Not a number"))) -> ◯ Not attempted | J10: COUNTIF on your Vendor column. | K10: =SUMPRODUCT(--ISNA(MATCH($B$9:$B$33,'Vendor Master'!$A$9:$A$33,0))) -> 4 | L10: =IFERROR(VLOOKUP(B10,'Vendor Master'!$A$9:$F$33,2,0),"Not in master") -> Tulip Printers
A11: B-2003 | B11: V014 | C11: 213900 | F11: 3 | G11: Total amount of those unmatched bills. | I11: =IF(ISBLANK(H11),"◯ Not attempted",IF(NOT(_xlfn.ISFORMULA(H11)),"✎ Use a formula",IF(ISNUMBER(H11),IF(ABS(H11-$K$11)<0.005,"✓ Correct","✗ Check again"),"✗ Not a number"))) -> ◯ Not attempted | J11: SUMIF with the same label. | K11: =SUMPRODUCT(ISNA(MATCH($B$9:$B$33,'Vendor Master'!$A$9:$A$33,0))*$C$9:$C$33) -> 563000 | L11: =IFERROR(VLOOKUP(B11,'Vendor Master'!$A$9:$F$33,2,0),"Not in master") -> Sunrise Packaging
A12: B-2004 | B12: V031 | C12: 244200 | F12: 4 | G12: Credit days for code V099 — show 0 if it's missing. | I12: =IF(ISBLANK(H12),"◯ Not attempted",IF(NOT(_xlfn.ISFORMULA(H12)),"✎ Use a formula",IF(ISNUMBER(H12),IF(ABS(H12-$K$12)<0.005,"✓ Correct","✗ Check again"),"✗ Not a number"))) -> ◯ Not attempted | J12: IFNA(…,0) | K12: =_xlfn.IFNA(VLOOKUP("V099",'Vendor Master'!$A$9:$F$33,5,0),0) -> 0 | L12: =IFERROR(VLOOKUP(B12,'Vendor Master'!$A$9:$F$33,2,0),"Not in master") -> Not in master
A13: B-2005 | B13: V003 | C13: 174500 | L13: =IFERROR(VLOOKUP(B13,'Vendor Master'!$A$9:$F$33,2,0),"Not in master") -> Sagar Metals
A14: B-2006 | B14: V021 | C14: 127100 | L14: =IFERROR(VLOOKUP(B14,'Vendor Master'!$A$9:$F$33,2,0),"Not in master") -> Harbour Shipping
A15: B-2007 | B15: V001 | C15: 9900 | L15: =IFERROR(VLOOKUP(B15,'Vendor Master'!$A$9:$F$33,2,0),"Not in master") -> Deccan Supplies
A16: B-2008 | B16: V018 | C16: 171700 | L16: =IFERROR(VLOOKUP(B16,'Vendor Master'!$A$9:$F$33,2,0),"Not in master") -> Crystal Glassworks
A17: B-2009 | B17: V008 | C17: 160800 | L17: =IFERROR(VLOOKUP(B17,'Vendor Master'!$A$9:$F$33,2,0),"Not in master") -> Vaibhav Textiles
A18: B-2010 | B18: V040 | C18: 36400 | L18: =IFERROR(VLOOKUP(B18,'Vendor Master'!$A$9:$F$33,2,0),"Not in master") -> Not in master
A19: B-2011 | B19: V025 | C19: 246200 | L19: =IFERROR(VLOOKUP(B19,'Vendor Master'!$A$9:$F$33,2,0),"Not in master") -> Silverline Tools
A20: B-2012 | B20: V005 | C20: 5300 | L20: =IFERROR(VLOOKUP(B20,'Vendor Master'!$A$9:$F$33,2,0),"Not in master") -> Bharat Electricals
A21: B-2013 | B21: V017 | C21: 139200 | L21: =IFERROR(VLOOKUP(B21,'Vendor Master'!$A$9:$F$33,2,0),"Not in master") -> Metro Freight
A22: B-2014 | B22: V014 | C22: 72100 | L22: =IFERROR(VLOOKUP(B22,'Vendor Master'!$A$9:$F$33,2,0),"Not in master") -> Sunrise Packaging
A23: B-2015 | B23: V002 | C23: 138100 | L23: =IFERROR(VLOOKUP(B23,'Vendor Master'!$A$9:$F$33,2,0),"Not in master") -> Orbit Systems
A24: B-2016 | B24: V099 | C24: 229700 | L24: =IFERROR(VLOOKUP(B24,'Vendor Master'!$A$9:$F$33,2,0),"Not in master") -> Not in master
... A33: B-2025 | B33: V020 | C33: 167000 | L33: =IFERROR(VLOOKUP(B33,'Vendor Master'!$A$9:$F$33,2,0),"Not in master") -> Pioneer Plastics

Sheet L6 Boss round — two-condition l
A1: LESSON 6 · BOSS ROUND — TWO-CONDITION LOOKUP
A2: ★★★★★ The price depends on product AND size. Find it without rearranging the price list.
A3: CONCEPT · Three routes: (1) a helper key column Product&"|"&Size on both sides; (2) SUMIFS as a lookup when each combination is unique; (3) INDEX(Price, MATCH(1,(Product=x)*(Size=y),0)) — array logic, where multiplying two tests means AND.
A8: Order | B8: Product | C8: Size | D8: Qty | E8: Price | F8: Value | H8: # | I8: Task | J8: Your answer | K8: Check | L8: Hint
A9: SO-001 | B9: Shirt | C9: M | D9: 36 | H9: 1 | I9: Fill Price for each order's product and size. | J9: → fill column E | K9: =IF(COUNTA($E$9:$E$33)=0,"◯ Not attempted",IF(NOT(_xlfn.ISFORMULA(E9)),"✎ Use a formula",IFERROR(IF(SUMPRODUCT(--(ABS($E$9:$E$33-$N$9:$N$33)<0.01))=ROWS($E$9:$E$33),"✓ Correct","✗ "&(ROWS($E$9:$E$33)-SUMPRODUCT(--(ABS($E$9:$E$33-$N$9:$N$33)<0.01)))&" rows differ"),"✗ Check the column"))) -> ◯ Not attempted | L9: SUMIFS(price column, product column, B9, size column, C9) | N9: =SUMIFS($K$16:$K$27,$I$16:$I$27,B9,$J$16:$J$27,C9) -> 430 | O9: =D9*SUMIFS($K$16:$K$27,$I$16:$I$27,B9,$J$16:$J$27,C9) -> 15480
A10: SO-002 | B10: Jacket | C10: L | D10: 16 | H10: 2 | I10: Fill Value = Qty × Price. | J10: → fill column F | K10: =IF(COUNTA($F$9:$F$33)=0,"◯ Not attempted",IF(NOT(_xlfn.ISFORMULA(F9)),"✎ Use a formula",IFERROR(IF(SUMPRODUCT(--(ABS($F$9:$F$33-$O$9:$O$33)<0.01))=ROWS($F$9:$F$33),"✓ Correct","✗ "&(ROWS($F$9:$F$33)-SUMPRODUCT(--(ABS($F$9:$F$33-$O$9:$O$33)<0.01)))&" rows differ"),"✗ Check the column"))) -> ◯ Not attempted | L10: =D9*E9 | N10: =SUMIFS($K$16:$K$27,$I$16:$I$27,B10,$J$16:$J$27,C10) -> 2350 | O10: =D10*SUMIFS($K$16:$K$27,$I$16:$I$27,B10,$J$16:$J$27,C10) -> 37600
A11: SO-003 | B11: Shirt | C11: M | D11: 44 | H11: 3 | I11: Total order value. | K11: =IF(ISBLANK(J11),"◯ Not attempted",IF(NOT(_xlfn.ISFORMULA(J11)),"✎ Use a formula",IF(ISNUMBER(J11),IF(ABS(J11-$M$11)<0.005,"✓ Correct","✗ Check again"),"✗ Not a number"))) -> ◯ Not attempted | L11: SUM your Value column. | M11: =D9*SUMIFS($K$16:$K$27,$I$16:$I$27,B9,$J$16:$J$27,C9)+D10*SUMIFS($K$16:$K$27,$I$16:$I$27,B10,$J$16:$J$27,C10)+D11*SUMIFS($K$16:$K$27,$I$16:$I$27,B11,$J$16:$J$27,C11)+D12*SUMIFS($K$16:$K$27,$I$16:$I$27,B12,$J$16:$J$27,C12)+D13*SUMIFS($K$16:$K$27,$I$16:$I$27,B13,$J$16:$J$27,C13)+D14*SUMIFS($K$16:$K$27,$I$16:$I$27,B14,$J$16:$J$27,C14)+D15*SUMIFS($K$16:$K$27,$I$16:$I$27,B15,$J$16:$J$27,C15)+D16*SUMIFS($K$16:$K$27,$I$16:$I$27,B16,$J$16:$J$27,C16)+D17*SUMIFS($K$16:$K$27,$I$16:$I$27,B17,$J$16:$J$27,C17)+D18*SUMIFS($K$16:$K$27,$I$16:$I$27,B18,$J$16:$J$27,C18)+D19*SUMIFS($K$16:$K$27,$I$16:$I$27,B19,$J$16:$J$27,C19)+D20*SUMIFS($K$16:$K$27,$I$16:$I$27,B20,$J$16:$J$27,C20)+D21*SUMIFS($K$16:$K$27,$I$16:$I$27,B21,$J$16:$J$27,C21)+D22*SUMIFS($K$16:$K$27,$I$16:$I$27,B22,$J$16:$J$27,C22)+D23*SUMIFS($K$16:$K$27,$I$16:$I$27,B23,$J$16:$J$27,C23)+D24*SUMIFS($K$16:$K$27,$I$16:$I$27,B24,$J$16:$J$27,C24)+D25*SUMIFS($K$16:$K$27,$I$16:$I$27,B25,$J$16:$J$27,C25)+D26*SUMIFS($K$16:$K$27,$I$16:$I$27,B26,$J$16:$J$27,C26)+D27*SUMIFS($K$16:$K$27,$I$16:$I$27,B27,$J$16:$J$27,C27)+D28*SUMIFS($K$16:$K$27,$I$16:$I$27,B28,$J$16:$J$27,C28)+D29*SUMIFS($K$16:$K$27,$I$16:$I$27,B29,$J$16:$J$27,C29)+D30*SUMIFS($K$16:$K$27,$I$16:$I$27,B30,$J$16:$J$27,C30)+D31*SUMIFS($K$16:$K$27,$I$16:$I$27,B31,$J$16:$J$27,C31)+D32*SUMIFS($K$16:$K$27,$I$16:$I$27,B32,$J$16:$J$27,C32)+D33*SUMIFS($K$16:$K$27,$I$16:$I$27,B33,$J$16:$J$27,C33) -> 713740 | N11: =SUMIFS($K$16:$K$27,$I$16:$I$27,B11,$J$16:$J$27,C11) -> 430 | O11: =D11*SUMIFS($K$16:$K$27,$I$16:$I$27,B11,$J$16:$J$27,C11) -> 18920
A12: SO-004 | B12: Shirt | C12: S | D12: 3 | H12: 4 | I12: How many units of size L were ordered in total? | K12: =IF(ISBLANK(J12),"◯ Not attempted",IF(NOT(_xlfn.ISFORMULA(J12)),"✎ Use a formula",IF(ISNUMBER(J12),IF(ABS(J12-$M$12)<0.005,"✓ Correct","✗ Check again"),"✗ Not a number"))) -> ◯ Not attempted | L12: SUMIF on size. | M12: =SUMIF($C$9:$C$33,"L",$D$9:$D$33) -> 240 | N12: =SUMIFS($K$16:$K$27,$I$16:$I$27,B12,$J$16:$J$27,C12) -> 660 | O12: =D12*SUMIFS($K$16:$K$27,$I$16:$I$27,B12,$J$16:$J$27,C12) -> 1980
A13: SO-005 | B13: Kurta | C13: L | D13: 10 | N13: =SUMIFS($K$16:$K$27,$I$16:$I$27,B13,$J$16:$J$27,C13) -> 1300 | O13: =D13*SUMIFS($K$16:$K$27,$I$16:$I$27,B13,$J$16:$J$27,C13) -> 13000
A14: SO-006 | B14: Jacket | C14: M | D14: 20 | I14: Price list (unique product + size) | N14: =SUMIFS($K$16:$K$27,$I$16:$I$27,B14,$J$16:$J$27,C14) -> 1310 | O14: =D14*SUMIFS($K$16:$K$27,$I$16:$I$27,B14,$J$16:$J$27,C14) -> 26200
A15: SO-007 | B15: Jacket | C15: L | D15: 31 | I15: Product | J15: Size | K15: Price | N15: =SUMIFS($K$16:$K$27,$I$16:$I$27,B15,$J$16:$J$27,C15) -> 2350 | O15: =D15*SUMIFS($K$16:$K$27,$I$16:$I$27,B15,$J$16:$J$27,C15) -> 72850
A16: SO-008 | B16: Kurta | C16: L | D16: 35 | I16: Shirt | J16: S | K16: 660 | N16: =SUMIFS($K$16:$K$27,$I$16:$I$27,B16,$J$16:$J$27,C16) -> 1300 | O16: =D16*SUMIFS($K$16:$K$27,$I$16:$I$27,B16,$J$16:$J$27,C16) -> 45500
A17: SO-009 | B17: Shirt | C17: L | D17: 31 | I17: Shirt | J17: M | K17: 430 | N17: =SUMIFS($K$16:$K$27,$I$16:$I$27,B17,$J$16:$J$27,C17) -> 850 | O17: =D17*SUMIFS($K$16:$K$27,$I$16:$I$27,B17,$J$16:$J$27,C17) -> 26350
A18: SO-010 | B18: Shirt | C18: M | D18: 8 | I18: Shirt | J18: L | K18: 850 | N18: =SUMIFS($K$16:$K$27,$I$16:$I$27,B18,$J$16:$J$27,C18) -> 430 | O18: =D18*SUMIFS($K$16:$K$27,$I$16:$I$27,B18,$J$16:$J$27,C18) -> 3440
A19: SO-011 | B19: Trouser | C19: M | D19: 11 | I19: Trouser | J19: S | K19: 1920 | N19: =SUMIFS($K$16:$K$27,$I$16:$I$27,B19,$J$16:$J$27,C19) -> 520 | O19: =D19*SUMIFS($K$16:$K$27,$I$16:$I$27,B19,$J$16:$J$27,C19) -> 5720
A20: SO-012 | B20: Jacket | C20: M | D20: 30 | I20: Trouser | J20: M | K20: 520 | N20: =SUMIFS($K$16:$K$27,$I$16:$I$27,B20,$J$16:$J$27,C20) -> 1310 | O20: =D20*SUMIFS($K$16:$K$27,$I$16:$I$27,B20,$J$16:$J$27,C20) -> 39300
A21: SO-013 | B21: Kurta | C21: M | D21: 38 | I21: Trouser | J21: L | K21: 2250 | N21: =SUMIFS($K$16:$K$27,$I$16:$I$27,B21,$J$16:$J$27,C21) -> 1160 | O21: =D21*SUMIFS($K$16:$K$27,$I$16:$I$27,B21,$J$16:$J$27,C21) -> 44080
A22: SO-014 | B22: Jacket | C22: S | D22: 49 | I22: Jacket | J22: S | K22: 410 | N22: =SUMIFS($K$16:$K$27,$I$16:$I$27,B22,$J$16:$J$27,C22) -> 410 | O22: =D22*SUMIFS($K$16:$K$27,$I$16:$I$27,B22,$J$16:$J$27,C22) -> 20090
A23: SO-015 | B23: Kurta | C23: S | D23: 22 | I23: Jacket | J23: M | K23: 1310 | N23: =SUMIFS($K$16:$K$27,$I$16:$I$27,B23,$J$16:$J$27,C23) -> 1590 | O23: =D23*SUMIFS($K$16:$K$27,$I$16:$I$27,B23,$J$16:$J$27,C23) -> 34980
A24: SO-016 | B24: Trouser | C24: M | D24: 47 | I24: Jacket | J24: L | K24: 2350 | N24: =SUMIFS($K$16:$K$27,$I$16:$I$27,B24,$J$16:$J$27,C24) -> 520 | O24: =D24*SUMIFS($K$16:$K$27,$I$16:$I$27,B24,$J$16:$J$27,C24) -> 24440
A25: SO-017 | B25: Shirt | C25: L | D25: 37 | I25: Kurta | J25: S | K25: 1590 | N25: =SUMIFS($K$16:$K$27,$I$16:$I$27,B25,$J$16:$J$27,C25) -> 850 | O25: =D25*SUMIFS($K$16:$K$27,$I$16:$I$27,B25,$J$16:$J$27,C25) -> 31450
A26: SO-018 | B26: Shirt | C26: M | D26: 38 | I26: Kurta | J26: M | K26: 1160 | N26: =SUMIFS($K$16:$K$27,$I$16:$I$27,B26,$J$16:$J$27,C26) -> 430 | O26: =D26*SUMIFS($K$16:$K$27,$I$16:$I$27,B26,$J$16:$J$27,C26) -> 16340
A27: SO-019 | B27: Kurta | C27: S | D27: 4 | I27: Kurta | J27: L | K27: 1300 | N27: =SUMIFS($K$16:$K$27,$I$16:$I$27,B27,$J$16:$J$27,C27) -> 1590 | O27: =D27*SUMIFS($K$16:$K$27,$I$16:$I$27,B27,$J$16:$J$27,C27) -> 6360
A28: SO-020 | B28: Shirt | C28: L | D28: 14 | N28: =SUMIFS($K$16:$K$27,$I$16:$I$27,B28,$J$16:$J$27,C28) -> 850 | O28: =D28*SUMIFS($K$16:$K$27,$I$16:$I$27,B28,$J$16:$J$27,C28) -> 11900
A29: SO-021 | B29: Jacket | C29: M | D29: 37 | N29: =SUMIFS($K$16:$K$27,$I$16:$I$27,B29,$J$16:$J$27,C29) -> 1310 | O29: =D29*SUMIFS($K$16:$K$27,$I$16:$I$27,B29,$J$16:$J$27,C29) -> 48470
A30: SO-022 | B30: Trouser | C30: L | D30: 26 | N30: =SUMIFS($K$16:$K$27,$I$16:$I$27,B30,$J$16:$J$27,C30) -> 2250 | O30: =D30*SUMIFS($K$16:$K$27,$I$16:$I$27,B30,$J$16:$J$27,C30) -> 58500
A31: SO-023 | B31: Shirt | C31: S | D31: 11 | N31: =SUMIFS($K$16:$K$27,$I$16:$I$27,B31,$J$16:$J$27,C31) -> 660 | O31: =D31*SUMIFS($K$16:$K$27,$I$16:$I$27,B31,$J$16:$J$27,C31) -> 7260
A32: SO-024 | B32: Jacket | C32: S | D32: 33 | N32: =SUMIFS($K$16:$K$27,$I$16:$I$27,B32,$J$16:$J$27,C32) -> 410 | O32: =D32*SUMIFS($K$16:$K$27,$I$16:$I$27,B32,$J$16:$J$27,C32) -> 13530
A33: SO-025 | B33: Trouser | C33: L | D33: 40 | N33: =SUMIFS($K$16:$K$27,$I$16:$I$27,B33,$J$16:$J$27,C33) -> 2250 | O33: =D33*SUMIFS($K$16:$K$27,$I$16:$I$27,B33,$J$16:$J$27,C33) -> 90000

Sheet Solutions
A1: SOLUTIONS & OTHER WAYS — open only after you have tried
A2: Model answers are shapes, not the only answer. If your formula gives the same result, it is right — compare the logic.
A4: L1 VLOOKUP exact match ★★
A5: # | B5: Task | C5: Answer cell | D5: Model formula | E5: Other ways | F5: Why it works
A6: 1 | B6: Fill Vendor: the vendor name for each bill's code. | C6: column D | D6: =VLOOKUP(B9,'Vendor Master'!$A$9:$F$33,2,0) (row 9, then fill down) | E6: =INDEX('Vendor Master'!$B$9:$B$33,MATCH(B9,'Vendor Master'!$A$9:$A$33,0)) =XLOOKUP(B9,'Vendor Master'!A9:A33,'Vendor Master'!B9:B33) | F6: Column 2 of the table is Vendor.
A7: 2 | B7: Fill Credit Days from the master. | C7: column E | D7: =VLOOKUP(B9,'Vendor Master'!$A$9:$F$33,5,0) (row 9, then fill down)
A8: 3 | B8: Which city is vendor V017 in? | C8: I11 | D8: =VLOOKUP("V017",'Vendor Master'!$A$9:$F$33,3,0)
A9: 4 | B9: Total amount billed by vendors on 45-day credit. | C9: I12 | D9: =SUMIF($E$9:$E$33,45,$C$9:$C$33)
A11: L2 Approximate match — slabs ★★★
A12: # | B12: Task | C12: Answer cell | D12: Model formula | E12: Other ways | F12: Why it works
A13: 1 | B13: Fill Rate: the commission rate for each salesperson's sales. | C13: column C | D13: =VLOOKUP(B9,$G$16:$H$20,2,TRUE) (row 9, then fill down) | E13: =LOOKUP(B9,From column,Rate column) =INDEX(Rate,MATCH(B9,From,1)) | F13: 3,00,000 isn't in the table; approximate match picks the 2,50,000 row.
A14: 2 | B14: Fill Commission = Sales × Rate, rounded to whole rupees. | C14: column D | D14: =ROUND(B9*C9,0) (row 9, then fill down)
A15: 3 | B15: Total commission payable. | C15: H11 | D15: =SUM($D$9:$D$28)
A16: 4 | B16: Commission rate for a sale of exactly ₹2,50,000. | C16: H12 | D16: =VLOOKUP(250000,$G$16:$H$20,2,TRUE)
A18: L3 INDEX-MATCH and left lookups ★★★
A19: # | B19: Task | C19: Answer cell | D19: Model formula | E19: Other ways | F19: Why it works
A20: 1 | B20: Fill Code: the vendor code for each PO's vendor name. | C20: column D | D20: =INDEX('Vendor Master'!$A$9:$A$33,MATCH(B9,'Vendor Master'!$B$9:$B$33,0)) (row 9, then fill down) | E20: =XLOOKUP(B9,'Vendor Master'!B9:B33,'Vendor Master'!A9:A33) | F20: VLOOKUP only returns columns to the RIGHT of the search column.
A21: 2 | B21: Fill GSTIN for each PO's vendor. | C21: column E | D21: =INDEX('Vendor Master'!$D$9:$D$33,MATCH(B9,'Vendor Master'!$B$9:$B$33,0)) (row 9, then fill down)
A22: 3 | B22: At what position in the master list does 'Metro Freight' appear? | C22: I11 | D22: =MATCH("Metro Freight",'Vendor Master'!$B$9:$B$33,0)
A23: 4 | B23: Category of the vendor on the largest PO. | C23: I12 | D23: =INDEX('Vendor Master'!$F$9:$F$33,MATCH(INDEX($B$9:$B$28,MATCH(MAX($C$9:$C$28),$C$9:$C$28,0)),'Vendor Master'!$B$9:$B$33,0)) | F23: Nesting one lookup inside another is normal — build it in two cells first if it helps.
A25: L4 Two-way lookup ★★★★
A26: # | B26: Task | C26: Answer cell | D26: Model formula | E26: Other ways | F26: Why it works
A27: 1 | B27: Fill Rate: the price for each order's product and region. | C27: column E | D27: =INDEX($J$16:$M$20,MATCH(B9,$I$16:$I$20,0),MATCH(C9,$J$15:$M$15,0)) (row 9, then fill down) | E27: =XLOOKUP(C9,regions,XLOOKUP(B9,products,body)) =SUMIFS(INDEX(body,0,MATCH(C9,regions,0)),products,B9) | F27: Two MATCHes give the coordinates; INDEX reads the crossing cell.
A28: 2 | B28: Fill Value = Qty × Rate. | C28: column F | D28: =D9*E9 (row 9, then fill down)
A29: 3 | B29: Total value of all orders. | C29: J11 | D29: =SUM($F$9:$F$33)
A30: 4 | B30: Rate for product P3 in the East region. | C30: J12 | D30: =INDEX($J$16:$M$20,MATCH("P3",$I$16:$I$20,0),MATCH("East",$J$15:$M$15,0))
A32: L5 Error-proof lookups ★★★★
A33: # | B33: Task | C33: Answer cell | D33: Model formula | E33: Other ways | F33: Why it works
A34: 1 | B34: Fill Vendor, showing "Not in master" when the code is missing. | C34: column D | D34: =IFERROR(VLOOKUP(B9,'Vendor Master'!$A$9:$F$33,2,0),"Not in master") (row 9, then fill down) | E34: =IFNA(VLOOKUP(B9,…,2,0),"Not in master") =XLOOKUP(B9,codes,names,"Not in master") | F34: The exceptions are the audit finding — label them, don't hide them.
A35: 2 | B35: How many bills have a code that isn't in the master? | C35: H10 | D35: =COUNTIF($D$9:$D$33,"Not in master") | E35: =SUMPRODUCT(--ISNA(MATCH(B9:B33,'Vendor Master'!A9:A33,0)))
A36: 3 | B36: Total amount of those unmatched bills. | C36: H11 | D36: =SUMIF($D$9:$D$33,"Not in master",$C$9:$C$33)
A37: 4 | B37: Credit days for code V099 — show 0 if it's missing. | C37: H12 | D37: =IFNA(VLOOKUP("V099",'Vendor Master'!$A$9:$F$33,5,0),0) | E37: =IFERROR(VLOOKUP("V099",…,5,0),0)
A39: L6 Boss round — two-condition l ★★★★★
A40: # | B40: Task | C40: Answer cell | D40: Model formula | E40: Other ways | F40: Why it works
A41: 1 | B41: Fill Price for each order's product and size. | C41: column E | D41: =SUMIFS(Price,Product,B9,Size,C9) | E41: =INDEX(Price,MATCH(1,(ProductCol=B9)*(SizeCol=C9),0)) =XLOOKUP(B9&"|"&C9,ProductCol&"|"&SizeCol,Price) Helper key =B9&"|"&C9 on both sides + VLOOKUP | F41: Each product-size pair appears once, so the 'sum' of matching prices is just the price.
A42: 2 | B42: Fill Value = Qty × Price. | C42: column F | D42: =D9*E9 (row 9, then fill down)
A43: 3 | B43: Total order value. | C43: J11 | D43: =SUM($F$9:$F$33)
A44: 4 | B44: How many units of size L were ordered in total? | C44: J12 | D44: =SUMIF($C$9:$C$33,"L",$D$9:$D$33)
